Workbook
Name ACC_: "ACCESORIO"
Name CAJA: [1]Val!$D$1:$D$20
Name CAJA: Val!$D$1:$D$20
Name CEL: [2]CEL!$A$4:$U$3920
Name CEL: [3]CEL!$A$4:$U$3920
Name d: [4]CEL!$A$5:$A$8860
Name DEST: [1]Val!$B$1:$B$7
Name DEST: Val!$B$1:$B$5
Name destino: Val!$B$1:$B$8
Name EQ: [1]Equipos!$A$4:$A$95
Name EQ: Equipos!$A$4:$A$85
Name Exa_: "EXACTA"
Name GAS: [1]Gastos!$A$2:$A$18
Name GAS: Gastos!$A$2:$A$18
Name Gas_: "GASTO"
Name item: [1]Val!$A$1:$A$28
Name item: Val!$A$1:$A$28
Name Kit_: "KIT"
Name mov: [1]Movimiento!$A$3:$A$99
Name mov: Movimiento!$A$3:$A$99
Name Prep_: "PREPAGA"
Name Prop_: "PROPIO"
Name Rep_: "REPOSICION"
Name Tarjeta: "{""Visa"" ; ""Master""}"
Name TDC: [1]Val!$E$1:$E$13
Name TDC: Val!$E$1:$E$13
Name VACIO: [1]Val!$G$1:$G$6
Name VACIO: Val!$G$1:$G$6
Name Var: [1]Val!$C$1:$C$11
Name Var: Val!$C$1:$C$11
Name Var_: "VARIO"

Sheet CAJA
A1: =MIN(A4:A2485) -> 45809 | B1: =IF(B2="",TODAY(),B2) -> 45918 | C1: EFE | D1: {=SUM(IF($J$4:$J$2485=C1,IF($A$4:$A$2485>=A1,IF($A$4:$A$2485<=$B$1,$D$4:$D$2485-$E$4:$E$2485,0),0),0))+J1} -> 446255.87 | F1: CC | G1: =SUMIF($I$4:$I$2485,"CC",$D$4:$D$2485)-SUMIFS($D$4:$D$2485,$G$4:$G$2485,"VARIO",$H$4:$H$2485,"PAGOCC")+L1 -> 0 | I1: EFE | J1: 1625077.9 | N1: =SUMIFS($D$4:$D$2485,$I$4:$I$2485,"MEN",$B$4:$B$2485,M1)-SUMIFS($D$4:$D$2485,$G$4:$G$2485,"VARIO",$H$4:$H$2485,"PAGOMEN",$B$4:$B$2485,M1) -> 0 | R1: 44923
A2: Otra | C2: CHE | D2: {=SUM(IF($K$4:$K$2485<>"",IF($J$4:$J$2485<>"EFE",IF($I$4:$I$2485="CAJA",IF($A$4:$A$2485>=A1,IF($A$4:$A$2485<=$B$1,$D$4:$D$2485-$E$4:$E$2485,0),0),0),0),0))+J2} -> 0 | F2: MEN | G2: =SUMIF($I$4:$I$2485,"MEN",$D$4:$D$2485)-SUMIFS($D$4:$D$2485,$G$4:$G$2485,"VARIO",$H$4:$H$2485,"PAGOMEN") -> 0 | I2: CHE | N2: =SUMIFS($D$4:$D$2485,$I$4:$I$2485,"MEN",$B$4:$B$2485,M2)-SUMIFS($D$4:$D$2485,$G$4:$G$2485,"VARIO",$H$4:$H$2485,"PAGOMEN",$B$4:$B$2485,M2) -> 0 | P2: Caja | Q2: =SUMIF(G:G,"ACCESORIO",D:D) -> 835436 | R2: =SUMIFS(D:D,G:G,"ACCESORIO",A:A,R1) -> 0
A3: FECHA | B3: DETALLE | C3: FAC. | D3: INGRESO | E3: SALIDA | F3: Cant | G3: OPERACIÓN | H3: TIPO/MODELO | I3: DEST | J3: MODO | K3: Nº | L3: Movim. | M3: OBSERVACIONES | P3: CajaAcc | Q3: =SUM(CajaAcc!D:D) -> 835436 | R3: =SUMIF(CajaAcc!A:A,R1,CajaAcc!D:D) -> 0
A4: 45809 | B4: Virtual | D4: 23350 | G4: orga | I4: caja | J4: efe | L4: 3rosario
A5: 45809 | B5: Diviani 3413436434 | D5: 500 | F5: 1 | G5: propio | H5: sim-car | I5: caja | J5: efe | L5: Enzo
A6: 45809 | B6: Moreno 3416659688 | D6: 500 | F6: 1 | G6: propio | H6: sim-car | I6: caja | J6: efe | L6: Shaiel
A7: 45809 | B7: Jambrina 3417566061 | D7: 500 | F7: 1 | G7: propio | H7: sim-car | I7: caja | J7: efe | L7: Shaiel
A8: 45809 | B8: Ponce 3416663933 | D8: 500 | F8: 1 | G8: propio | H8: sim-car | I8: caja | J8: efe | L8: Shaiel
A9: 45809 | B9: Consumidor final | D9: 23500 | G9: accesorio | I9: caja | J9: efe | L9: 3rosario
A10: 45809 | B10: Transfer | E10: 5500 | F10: 1 | G10: vario | H10: transfer | I10: caja | J10: efe | K10: 5J8LQ | L10: SantanderC | M10: QR
A11: 45809 | B11: Consumidor final | D11: 24000 | F11: 3 | G11: accesorio | I11: tdc | J11: visa | K11: 561 | L11: 3rosario | M11: Débito
A12: 45809 | B12: Merino 3476309370 | F12: 1 | G12: cater | L12: Enzo | M12: tc-cti $425999
A13: 45809 | B13: Ruiz 3413568354 | D13: 500 | F13: 1 | G13: propio | H13: sim-car | I13: caja | J13: efe | L13: Shaiel
A14: 45809 | B14: Ghone 3416149014 | D14: 500 | F14: 1 | G14: propio | H14: sim-car | I14: caja | J14: efe | L14: Shaiel
A15: 45809 | B15: Cardozo 3415150634 | D15: 500 | F15: 1 | G15: propio | H15: sim-car | I15: caja | J15: efe | L15: Shaiel
A16: 45809 | B16: Torres 3476547387 | D16: 500 | F16: 1 | G16: propio | H16: sim-car | I16: caja | J16: efe | L16: Shaiel
A17: 45809 | B17: Donatti 3416935120 | D17: 500 | F17: 1 | G17: propio | H17: sim-car | I17: caja | J17: efe | L17: Shaiel
A18: 45809 | B18: Consumidor final | D18: 19500 | F18: 2 | G18: accesorio | I18: tdc | J18: visa | K18: 562 | L18: 3rosario | M18: Débito
A19: 45810 | B19: Transfer | D19: =50800+10000+60000+20000+84000 -> 224800 | F19: 1 | G19: vario | H19: transfer | I19: caja | J19: efe | L19: D1175 | M19: CONTROL OK
A20: 45810 | B20: Transfer sim | C20: 0337 | F20: 10 | G20: propio | H20: sim-car | L20: 5corrientes
A21: 45810 | B21: Garcia 3415016311 | F21: 1 | G21: cater | L21: Lucila | M21: tc-cti $199999
A22: 45810 | B22: Serra 3417419992 | F22: 1 | G22: r2g | H22: sim-car | L22: Lucila
A23: 45810 | B23: Dalinger 3415836150 | F23: 1 | G23: cater | L23: Lucila | M23: tc-cti $425999
A24: 45810 | B24: Fernandez 3412783594 | D24: 500 | F24: 1 | G24: propio | H24: sim-car | I24: caja | J24: efe | L24: Lucila
A25: 45810 | B25: Villagomez 3417433519 | F25: 1 | G25: r2g | H25: sim-car | L25: Lucila
A26: 45810 | B26: Acosta 3417465441 | D26: 500 | F26: 1 | G26: propio | H26: sim-car | I26: caja | J26: efe | L26: Enzo
A27: 45810 | B27: Ovejero 3415529102 | D27: 500 | F27: 1 | G27: propio | H27: sim-car | I27: caja | J27: efe | L27: Enzo
A28: 45810 | B28: Petracca 3415441865 | F28: 1 | G28: cater | L28: Lucila | M28: Financiado
A29: 45810 | B29: Maradona 3413402468 | D29: 500 | F29: 1 | G29: propio | H29: sim-car | I29: caja | J29: efe | L29: Enzo
A30: 45810 | B30: Medina 3413844671 | D30: 500 | F30: 1 | G30: propio | H30: sim-car | I30: caja | J30: efe | L30: Lucila
A31: 45810 | B31: Soroeta 9992991025 | F31: 1 | G31: portap | H31: sim-car | L31: Enzo
A32: 45810 | B32: Soroeta 9992991145 | F32: 1 | G32: portap | H32: sim-car | L32: Enzo
A33: 45810 | B33: Soroeta 9992992029 | F33: 1 | G33: portap | H33: sim-car | L33: Enzo
A34: 45810 | B34: Consumidor final | D34: 29500 | G34: accesorio | I34: caja | J34: efe | L34: 3rosario
A35: 45810 | B35: Martin, Andres | F35: 1 | G35: baf | L35: Lucila
A36: 45810 | B36: Facundo Elias Leiva | F36: 1 | G36: baf | L36: Shaiel
A37: 45811 | B37: Transfer | D37: =174000+38000+3000+41000 -> 256000 | F37: 1 | G37: vario | H37: transfer | I37: caja | J37: efe | L37: D1175 | M37: CONTROL OK
A38: 45811 | B38: Carga virtual | D38: -104000 | G38: orga | I38: caja | J38: efe | L38: 3rosario
A39: 45811 | B39: Carga virtual | E39: -5500 | G39: gasto | H39: comision | I39: caja | J39: efe | L39: 3rosario
A40: 45811 | B40: Virtual | D40: 47500 | G40: orga | I40: caja | J40: efe | L40: 3rosario
A41: 45811 | B41: Biñoli 3417457830 | F41: 1 | G41: r2g | H41: sim-car | L41: Lucila
A42: 45811 | B42: Chaparro 3415994161 | D42: 500 | F42: 1 | G42: propio | H42: sim-car | I42: caja | J42: efe | L42: Enzo
A43: 45811 | B43: Guglielmo 1160229462 | D43: 500 | F43: 1 | G43: propio | H43: sim-car | I43: caja | J43: efe | L43: Enzo
A44: 45811 | B44: Vache 3415886684 | D44: 500 | F44: 1 | G44: propio | H44: sim-car | I44: caja | J44: efe | L44: Enzo
A45: 45811 | B45: NADIA GODOY | F45: 1 | G45: baf | L45: Lucila
A46: 45812 | B46: Transfer | D46: =39000+28000+34000 -> 101000 | F46: 1 | G46: vario | H46: transfer | I46: caja | J46: efe | L46: D1175 | M46: CONTROL OK
A47: 45812 | B47: Irruta 3416168973 | D47: 500 | F47: 1 | G47: propio | H47: sim-car | I47: caja | J47: efe | L47: Shaiel
A48: 45812 | B48: Irruta 3416168973 | F48: 1 | G48: cater | L48: Shaiel | M48: tc-cti $212499
A49: 45812 | B49: Lopez 3417404308 | D49: 500 | F49: 1 | G49: propio | H49: sim-car | I49: caja | J49: efe | L49: Shaiel
A50: 45812 | B50: Reposicion sim | F50: -12 | G50: propio | H50: sim-1175 | L50: conciliacion
A51: 45812 | B51: Consumidor final | D51: 23500 | G51: accesorio | I51: caja | J51: efe | L51: 3rosario
A52: 45812 | B52: Transfer | E52: 10500 | F52: 1 | G52: vario | H52: transfer | I52: caja | J52: efe | K52: V50P3 | L52: SantanderC | M52: QR
A53: 45812 | B53: Figueroa 3416987445 | D53: 500 | F53: 1 | G53: propio | H53: sim-car | I53: caja | J53: efe | L53: Enzo
A54: 45812 | B54: Santibañez 3413257234 | F54: 1 | G54: r2g | H54: sim-car | L54: Enzo
A55: 45812 | B55: Valentini 3413191861 | D55: 500 | F55: 1 | G55: propio | H55: sim-car | I55: caja | J55: efe | L55: Enzo
A56: 45812 | B56: Zehnder Eliana E y Zehnder Luciano A. S.H. | F56: 1 | G56: baf | L56: Enzo
A57: 45812 | B57: Zehnder Eliana E y Zehnder Luciano A. S.H. | F57: 1 | G57: baf | L57: Enzo
A58: 45813 | B58: Transfer | D58: =5000+40000+55000+31000 -> 131000 | F58: 1 | G58: vario | H58: transfer | I58: caja | J58: efe | L58: D1175
A59: 45813 | B59: Ameli 3415662841 | F59: 1 | G59: cater | L59: Lucila | M59: tc-cti $199999
A60: 45813 | B60: Simonetti 3413032043 | D60: 500 | F60: 1 | G60: propio | H60: sim-car | I60: caja | J60: efe | L60: Lucila
A61: 45813 | B61: Consumidor final | D61: 4500 | G61: accesorio | I61: caja | J61: efe | L61: 3rosario
A62: 45813 | B62: Consumidor final | D62: 7500 | F62: 1 | G62: accesorio | I62: tdc | J62: visa | K62: 563 | L62: 3rosario | M62: Débito
A63: 45813 | B63: Enriquez 9994611445 | F63: 2 | G63: p7g | H63: sim-car | L63: Shaiel
A64: 45813 | B64: Dominguez 3417463270 | F64: 1 | G64: r4g | H64: sim-car | L64: Lucila
A65: 45813 | B65: Wild 3417463343 | F65: 1 | G65: r2g | H65: sim-car | L65: Shaiel
A66: 45813 | B66: Virtual | D66: 7500 | G66: orga | I66: caja | J66: efe | L66: 3rosario
A67: 45813 | B67: Consumidor final | D67: 300 | F67: 3 | G67: propio | H67: sim-1175 | I67: caja | J67: efe | L67: 3rosario
A68: 45814 | B68: Transfer | D68: =12000+77600+18000+35000+5000 -> 147600 | F68: 1 | G68: vario | H68: transfer | I68: caja | J68: efe | L68: D1175
A69: 45814 | B69: Amado 9994616426 | F69: 1 | G69: p7g | H69: sim-car | L69: Lucila
A70: 45814 | B70: Amado 9994616490 | F70: 1 | G70: p7g | H70: sim-car | L70: Lucila
A71: 45814 | B71: Amado 9994616656 | F71: 1 | G71: p7g | H71: sim-car | L71: Lucila
A72: 45814 | B72: Rojas 3412168135 | D72: 500 | F72: 1 | G72: propio | H72: sim-car | I72: caja | J72: efe | L72: Lucila
A73: 45814 | B73: Dominguez 3417464278 | F73: 1 | G73: r4g | H73: sim-car | L73: Enzo
A74: 45814 | B74: Dominguez 3417464278 | D74: 0 | F74: 1 | G74: propio | H74: sim-car | I74: caja | J74: efe | L74: Enzo | M74: E-SIM
A75: 45814 | B75: Flitter 3417478216 | D75: 500 | F75: 1 | G75: propio | H75: sim-car | I75: caja | J75: efe | L75: Enzo
A76: 45814 | B76: Joansen 3417505174 | D76: 500 | F76: 1 | G76: propio | H76: sim-car | I76: caja | J76: efe | L76: Enzo
A77: 45814 | B77: Bustamante 3413353963 | D77: 500 | F77: 1 | G77: propio | H77: sim-car | I77: caja | J77: efe | L77: Enzo
A78: 45814 | B78: Grimao, Shaiel | E78: 24333.012 | F78: 1 | G78: gasto | H78: sueldos | I78: caja | J78: efe | L78: 3rosario
A79: 45815 | B79: Limpieza vidrios | E79: 10000 | F79: 1 | G79: gasto | H79: limpieza | I79: caja | J79: efe | L79: 3rosario
A80: 45815 | B80: Limpieza | E80: 10000 | F80: 1 | G80: gasto | H80: limpieza | I80: caja | J80: efe | L80: 3rosario
A81: 45815 | B81: Lopez 3417477857 | F81: 1 | G81: r2g | H81: sim-car | L81: Enzo
A82: 45815 | B82: Guitierrez 3417477860 | F82: 1 | G82: r2g | H82: sim-car | L82: Enzo
A83: 45815 | B83: Werner 3417477900 | F83: 1 | G83: r2g | H83: sim-car | L83: Shaiel
A84: 45815 | B84: Echarren 3415318163 | D84: 500 | F84: 1 | G84: propio | H84: sim-car | I84: caja | J84: efe | L84: 3rosario
A85: 45815 | B85: Ratto 3415200322 | D85: 500 | F85: 1 | G85: propio | H85: sim-car | I85: caja | J85: efe | L85: 3rosario
A86: 45815 | B86: Consumidor final | D86: 10500 | F86: 2 | G86: accesorio | I86: tdc | J86: visa | K86: 564 | L86: 3rosario | M86: $10762,50 1cta.
A87: 45815 | B87: Consumidor final | D87: 61000 | G87: accesorio | I87: caja | J87: efe | L87: 3rosario
A88: 45815 | B88: Tibaldi 3413494830 | D88: 500 | F88: 1 | G88: propio | H88: sim-car | I88: caja | J88: efe | L88: Shaiel
A89: 45815 | B89: Torres 3413791629 | D89: 500 | F89: 1 | G89: propio | H89: sim-car | I89: caja | J89: efe | L89: Shaiel
A90: 45815 | B90: Salvatierra 3415992494 | F90: 1 | G90: cater | L90: Shaiel | M90: Financiado
A91: 45815 | B91: Virtual | D91: 3000 | G91: orga | I91: caja | J91: efe | L91: 3rosario
A92: 45815 | B92: Salva 3413029250 | F92: 1 | G92: cater | L92: Shaiel | M92: Financiado
A93: 45815 | B93: Transfer | E93: 32000 | F93: 1 | G93: vario | H93: transfer | I93: caja | J93: efe | K93: 52928 | L93: SantanderC | M93: $35815,28 QR 2cta.
A94: 45816 | B94: Consumidor final | D94: 16500 | G94: accesorio | I94: caja | J94: efe | L94: 3rosario
A95: 45816 | B95: Gonzalez 3415780780 | F95: 1 | G95: cater | L95: Shaiel | M95: tc-cti $340799
A96: 45816 | B96: Carey 3415456072 | D96: 500 | F96: 1 | G96: propio | H96: sim-car | I96: caja | J96: efe | L96: Shaiel
A97: 45816 | B97: Montes 3413468452 | D97: 500 | F97: 1 | G97: propio | H97: sim-car | I97: caja | J97: efe | L97: Shaiel
A98: 45816 | B98: Gonzalez 347653991 | D98: 500 | F98: 1 | G98: propio | H98: sim-car | I98: caja | J98: efe | L98: Shaiel
A99: 45816 | B99: Consumidor final | D99: 200 | F99: 2 | G99: propio | H99: sim-1175 | I99: caja | J99: efe | L99: 3rosario
A100: 45816 | B100: Virtual | D100: 7500 | G100: orga | I100: caja | J100: efe | L100: 3rosario
...

Sheet CC
A1: Cliente | B1: Saldo | C1: Monto | D1: Cuota | E1: Cantidad | F1: Fecha | G1: Reclamar | H1: Pago | I1: Actual | J1: Situación | M1: Monto | N1: Cuotas | O1: MontoCuota
G2: =B2+D2*(IF(12*(+LEFT(MID(CELL("nombrearchivo",A1),FIND(".xlsx",CELL("nombrearchivo",A1))-4,4),2)-RIGHT(YEAR(F2),2))+RIGHT(MID(CELL("nombrearchivo",A1),FIND(".xlsx",CELL("nombrearchivo",A1))-4,4),2)-MONTH(F2)>E2,0,1)) -> 0 | H2: =SUMIFS(CAJA!D:D,CAJA!G:G,"VARIO",CAJA!H:H,"PAGO*",CAJA!B:B,A2) -> 0 | I2: =G2-H2 -> 0 | J2: =IF(I2>D2,"MOROSO",IF(I2>0,"COBRAR CUOTA","NORMAL")) -> NORMAL | M2: 500 | N2: 3 | O2: 180
G3: =B3+D3*(IF(12*(+LEFT(MID(CELL("nombrearchivo",A2),FIND(".xlsx",CELL("nombrearchivo",A2))-4,4),2)-RIGHT(YEAR(F3),2))+RIGHT(MID(CELL("nombrearchivo",A2),FIND(".xlsx",CELL("nombrearchivo",A2))-4,4),2)-MONTH(F3)>E3,0,1)) -> 0 | H3: =SUMIFS(CAJA!D:D,CAJA!G:G,"VARIO",CAJA!H:H,"PAGO*",CAJA!B:B,A3) -> 0 | I3: =G3-H3 -> 0 | J3: =IF(I3>D3,"MOROSO",IF(I3>0,"COBRAR CUOTA","NORMAL")) -> NORMAL | M3: 500 | N3: 6 | O3: 108
G4: =B4+D4*(IF(12*(+LEFT(MID(CELL("nombrearchivo",A3),FIND(".xlsx",CELL("nombrearchivo",A3))-4,4),2)-RIGHT(YEAR(F4),2))+RIGHT(MID(CELL("nombrearchivo",A3),FIND(".xlsx",CELL("nombrearchivo",A3))-4,4),2)-MONTH(F4)>E4,0,1)) -> 0 | H4: =SUMIFS(CAJA!D:D,CAJA!G:G,"VARIO",CAJA!H:H,"PAGO*",CAJA!B:B,A4) -> 0 | I4: =G4-H4 -> 0 | J4: =IF(I4>D4,"MOROSO",IF(I4>0,"COBRAR CUOTA","NORMAL")) -> NORMAL | M4: 1000 | N4: 3 | O4: 380
G5: =B5+D5*(IF(12*(+LEFT(MID(CELL("nombrearchivo",A4),FIND(".xlsx",CELL("nombrearchivo",A4))-4,4),2)-RIGHT(YEAR(F5),2))+RIGHT(MID(CELL("nombrearchivo",A4),FIND(".xlsx",CELL("nombrearchivo",A4))-4,4),2)-MONTH(F5)>E5,0,1)) -> 0 | H5: =SUMIFS(CAJA!D:D,CAJA!G:G,"VARIO",CAJA!H:H,"PAGO*",CAJA!B:B,A5) -> 0 | I5: =G5-H5 -> 0 | J5: =IF(I5>D5,"MOROSO",IF(I5>0,"COBRAR CUOTA","NORMAL")) -> NORMAL | M5: 1000 | N5: 6 | O5: 216
G6: =B6+D6*(IF(12*(+LEFT(MID(CELL("nombrearchivo",A5),FIND(".xlsx",CELL("nombrearchivo",A5))-4,4),2)-RIGHT(YEAR(F6),2))+RIGHT(MID(CELL("nombrearchivo",A5),FIND(".xlsx",CELL("nombrearchivo",A5))-4,4),2)-MONTH(F6)>E6,0,1)) -> 0 | H6: =SUMIFS(CAJA!D:D,CAJA!G:G,"VARIO",CAJA!H:H,"PAGO*",CAJA!B:B,A6) -> 0 | I6: =G6-H6 -> 0 | J6: =IF(I6>D6,"MOROSO",IF(I6>0,"COBRAR CUOTA","NORMAL")) -> NORMAL | M6: 1000 | N6: 10 | O6: 150
G7: =B7+D7*(IF(12*(+LEFT(MID(CELL("nombrearchivo",A6),FIND(".xlsx",CELL("nombrearchivo",A6))-4,4),2)-RIGHT(YEAR(F7),2))+RIGHT(MID(CELL("nombrearchivo",A6),FIND(".xlsx",CELL("nombrearchivo",A6))-4,4),2)-MONTH(F7)>E7,0,1)) -> 0 | H7: =SUMIFS(CAJA!D:D,CAJA!G:G,"VARIO",CAJA!H:H,"PAGO*",CAJA!B:B,A7) -> 0 | I7: =G7-H7 -> 0 | J7: =IF(I7>D7,"MOROSO",IF(I7>0,"COBRAR CUOTA","NORMAL")) -> NORMAL | M7: 5000 | N7: 3 | O7: 1900
G8: =B8+D8*(IF(12*(+LEFT(MID(CELL("nombrearchivo",A7),FIND(".xlsx",CELL("nombrearchivo",A7))-4,4),2)-RIGHT(YEAR(F8),2))+RIGHT(MID(CELL("nombrearchivo",A7),FIND(".xlsx",CELL("nombrearchivo",A7))-4,4),2)-MONTH(F8)>E8,0,1)) -> 0 | H8: =SUMIFS(CAJA!D:D,CAJA!G:G,"VARIO",CAJA!H:H,"PAGO*",CAJA!B:B,A8) -> 0 | I8: =G8-H8 -> 0 | J8: =IF(I8>D8,"MOROSO",IF(I8>0,"COBRAR CUOTA","NORMAL")) -> NORMAL | M8: 5000 | N8: 6 | O8: 1080
G9: =B9+D9*(IF(12*(+LEFT(MID(CELL("nombrearchivo",A8),FIND(".xlsx",CELL("nombrearchivo",A8))-4,4),2)-RIGHT(YEAR(F9),2))+RIGHT(MID(CELL("nombrearchivo",A8),FIND(".xlsx",CELL("nombrearchivo",A8))-4,4),2)-MONTH(F9)>E9,0,1)) -> 0 | H9: =SUMIFS(CAJA!D:D,CAJA!G:G,"VARIO",CAJA!H:H,"PAGO*",CAJA!B:B,A9) -> 0 | I9: =G9-H9 -> 0 | J9: =IF(I9>D9,"MOROSO",IF(I9>0,"COBRAR CUOTA","NORMAL")) -> NORMAL | M9: 5000 | N9: 10 | O9: 750
G10: =B10+D10*(IF(12*(+LEFT(MID(CELL("nombrearchivo",A9),FIND(".xlsx",CELL("nombrearchivo",A9))-4,4),2)-RIGHT(YEAR(F10),2))+RIGHT(MID(CELL("nombrearchivo",A9),FIND(".xlsx",CELL("nombrearchivo",A9))-4,4),2)-MONTH(F10)>E10,0,1)) -> 0 | H10: =SUMIFS(CAJA!D:D,CAJA!G:G,"VARIO",CAJA!H:H,"PAGO*",CAJA!B:B,A10) -> 0 | I10: =G10-H10 -> 0 | J10: =IF(I10>D10,"MOROSO",IF(I10>0,"COBRAR CUOTA","NORMAL")) -> NORMAL | M10: 5000 | N10: 12 | O10: 670
G11: =B11+D11*(IF(12*(+LEFT(MID(CELL("nombrearchivo",A10),FIND(".xlsx",CELL("nombrearchivo",A10))-4,4),2)-RIGHT(YEAR(F11),2))+RIGHT(MID(CELL("nombrearchivo",A10),FIND(".xlsx",CELL("nombrearchivo",A10))-4,4),2)-MONTH(F11)>E11,0,1)) -> 0 | H11: =SUMIFS(CAJA!D:D,CAJA!G:G,"VARIO",CAJA!H:H,"PAGO*",CAJA!B:B,A11) -> 0 | I11: =G11-H11 -> 0 | J11: =IF(I11>D11,"MOROSO",IF(I11>0,"COBRAR CUOTA","NORMAL")) -> NORMAL | M11: 5000 | N11: 18 | O11: 540
G12: =B12+D12*(IF(12*(+LEFT(MID(CELL("nombrearchivo",A11),FIND(".xlsx",CELL("nombrearchivo",A11))-4,4),2)-RIGHT(YEAR(F12),2))+RIGHT(MID(CELL("nombrearchivo",A11),FIND(".xlsx",CELL("nombrearchivo",A11))-4,4),2)-MONTH(F12)>E12,0,1)) -> 0 | H12: =SUMIFS(CAJA!D:D,CAJA!G:G,"VARIO",CAJA!H:H,"PAGO*",CAJA!B:B,A12) -> 0 | I12: =G12-H12 -> 0 | J12: =IF(I12>D12,"MOROSO",IF(I12>0,"COBRAR CUOTA","NORMAL")) -> NORMAL | M12: 10000 | N12: 18 | O12: 1080
G13: =B13+D13*(IF(12*(+LEFT(MID(CELL("nombrearchivo",A12),FIND(".xlsx",CELL("nombrearchivo",A12))-4,4),2)-RIGHT(YEAR(F13),2))+RIGHT(MID(CELL("nombrearchivo",A12),FIND(".xlsx",CELL("nombrearchivo",A12))-4,4),2)-MONTH(F13)>E13,0,1)) -> 0 | H13: =SUMIFS(CAJA!D:D,CAJA!G:G,"VARIO",CAJA!H:H,"PAGO*",CAJA!B:B,A13) -> 0 | I13: =G13-H13 -> 0 | J13: =IF(I13>D13,"MOROSO",IF(I13>0,"COBRAR CUOTA","NORMAL")) -> NORMAL | M13: 15000 | N13: 18 | O13: 1620
G14: =B14+D14*(IF(12*(+LEFT(MID(CELL("nombrearchivo",A13),FIND(".xlsx",CELL("nombrearchivo",A13))-4,4),2)-RIGHT(YEAR(F14),2))+RIGHT(MID(CELL("nombrearchivo",A13),FIND(".xlsx",CELL("nombrearchivo",A13))-4,4),2)-MONTH(F14)>E14,0,1)) -> 0 | H14: =SUMIFS(CAJA!D:D,CAJA!G:G,"VARIO",CAJA!H:H,"PAGO*",CAJA!B:B,A14) -> 0 | I14: =G14-H14 -> 0 | J14: =IF(I14>D14,"MOROSO",IF(I14>0,"COBRAR CUOTA","NORMAL")) -> NORMAL | M14: 20000 | N14: 18 | O14: 2160
G15: =B15+D15*(IF(12*(+LEFT(MID(CELL("nombrearchivo",A14),FIND(".xlsx",CELL("nombrearchivo",A14))-4,4),2)-RIGHT(YEAR(F15),2))+RIGHT(MID(CELL("nombrearchivo",A14),FIND(".xlsx",CELL("nombrearchivo",A14))-4,4),2)-MONTH(F15)>E15,0,1)) -> 0 | H15: =SUMIFS(CAJA!D:D,CAJA!G:G,"VARIO",CAJA!H:H,"PAGO*",CAJA!B:B,A15) -> 0 | I15: =G15-H15 -> 0 | J15: =IF(I15>D15,"MOROSO",IF(I15>0,"COBRAR CUOTA","NORMAL")) -> NORMAL
G16: =B16+D16*(IF(12*(+LEFT(MID(CELL("nombrearchivo",A15),FIND(".xlsx",CELL("nombrearchivo",A15))-4,4),2)-RIGHT(YEAR(F16),2))+RIGHT(MID(CELL("nombrearchivo",A15),FIND(".xlsx",CELL("nombrearchivo",A15))-4,4),2)-MONTH(F16)>E16,0,1)) -> 0 | H16: =SUMIFS(CAJA!D:D,CAJA!G:G,"VARIO",CAJA!H:H,"PAGO*",CAJA!B:B,A16) -> 0 | I16: =G16-H16 -> 0 | J16: =IF(I16>D16,"MOROSO",IF(I16>0,"COBRAR CUOTA","NORMAL")) -> NORMAL
G17: =B17+D17*(IF(12*(+LEFT(MID(CELL("nombrearchivo",A16),FIND(".xlsx",CELL("nombrearchivo",A16))-4,4),2)-RIGHT(YEAR(F17),2))+RIGHT(MID(CELL("nombrearchivo",A16),FIND(".xlsx",CELL("nombrearchivo",A16))-4,4),2)-MONTH(F17)>E17,0,1)) -> 0 | H17: =SUMIFS(CAJA!D:D,CAJA!G:G,"VARIO",CAJA!H:H,"PAGO*",CAJA!B:B,A17) -> 0 | I17: =G17-H17 -> 0 | J17: =IF(I17>D17,"MOROSO",IF(I17>0,"COBRAR CUOTA","NORMAL")) -> NORMAL
G18: =B18+D18*(IF(12*(+LEFT(MID(CELL("nombrearchivo",A17),FIND(".xlsx",CELL("nombrearchivo",A17))-4,4),2)-RIGHT(YEAR(F18),2))+RIGHT(MID(CELL("nombrearchivo",A17),FIND(".xlsx",CELL("nombrearchivo",A17))-4,4),2)-MONTH(F18)>E18,0,1)) -> 0 | H18: =SUMIFS(CAJA!D:D,CAJA!G:G,"VARIO",CAJA!H:H,"PAGO*",CAJA!B:B,A18) -> 0 | I18: =G18-H18 -> 0 | J18: =IF(I18>D18,"MOROSO",IF(I18>0,"COBRAR CUOTA","NORMAL")) -> NORMAL
G19: =B19+D19*(IF(12*(+LEFT(MID(CELL("nombrearchivo",A18),FIND(".xlsx",CELL("nombrearchivo",A18))-4,4),2)-RIGHT(YEAR(F19),2))+RIGHT(MID(CELL("nombrearchivo",A18),FIND(".xlsx",CELL("nombrearchivo",A18))-4,4),2)-MONTH(F19)>E19,0,1)) -> 0 | H19: =SUMIFS(CAJA!D:D,CAJA!G:G,"VARIO",CAJA!H:H,"PAGO*",CAJA!B:B,A19) -> 0 | I19: =G19-H19 -> 0 | J19: =IF(I19>D19,"MOROSO",IF(I19>0,"COBRAR CUOTA","NORMAL")) -> NORMAL
G20: =B20+D20*(IF(12*(+LEFT(MID(CELL("nombrearchivo",A19),FIND(".xlsx",CELL("nombrearchivo",A19))-4,4),2)-RIGHT(YEAR(F20),2))+RIGHT(MID(CELL("nombrearchivo",A19),FIND(".xlsx",CELL("nombrearchivo",A19))-4,4),2)-MONTH(F20)>E20,0,1)) -> 0 | H20: =SUMIFS(CAJA!D:D,CAJA!G:G,"VARIO",CAJA!H:H,"PAGO*",CAJA!B:B,A20) -> 0 | I20: =G20-H20 -> 0 | J20: =IF(I20>D20,"MOROSO",IF(I20>0,"COBRAR CUOTA","NORMAL")) -> NORMAL
G21: =B21+D21*(IF(12*(+LEFT(MID(CELL("nombrearchivo",A20),FIND(".xlsx",CELL("nombrearchivo",A20))-4,4),2)-RIGHT(YEAR(F21),2))+RIGHT(MID(CELL("nombrearchivo",A20),FIND(".xlsx",CELL("nombrearchivo",A20))-4,4),2)-MONTH(F21)>E21,0,1)) -> 0 | H21: =SUMIFS(CAJA!D:D,CAJA!G:G,"VARIO",CAJA!H:H,"PAGO*",CAJA!B:B,A21) -> 0 | I21: =G21-H21 -> 0 | J21: =IF(I21>D21,"MOROSO",IF(I21>0,"COBRAR CUOTA","NORMAL")) -> NORMAL
G22: =B22+D22*(IF(12*(+LEFT(MID(CELL("nombrearchivo",A21),FIND(".xlsx",CELL("nombrearchivo",A21))-4,4),2)-RIGHT(YEAR(F22),2))+RIGHT(MID(CELL("nombrearchivo",A21),FIND(".xlsx",CELL("nombrearchivo",A21))-4,4),2)-MONTH(F22)>E22,0,1)) -> 0 | H22: =SUMIFS(CAJA!D:D,CAJA!G:G,"VARIO",CAJA!H:H,"PAGO*",CAJA!B:B,A22) -> 0 | I22: =G22-H22 -> 0 | J22: =IF(I22>D22,"MOROSO",IF(I22>0,"COBRAR CUOTA","NORMAL")) -> NORMAL
G23: =B23+D23*(IF(12*(+LEFT(MID(CELL("nombrearchivo",A22),FIND(".xlsx",CELL("nombrearchivo",A22))-4,4),2)-RIGHT(YEAR(F23),2))+RIGHT(MID(CELL("nombrearchivo",A22),FIND(".xlsx",CELL("nombrearchivo",A22))-4,4),2)-MONTH(F23)>E23,0,1)) -> 0 | H23: =SUMIFS(CAJA!D:D,CAJA!G:G,"VARIO",CAJA!H:H,"PAGO*",CAJA!B:B,A23) -> 0 | I23: =G23-H23 -> 0 | J23: =IF(I23>D23,"MOROSO",IF(I23>0,"COBRAR CUOTA","NORMAL")) -> NORMAL
G24: =B24+D24*(IF(12*(+LEFT(MID(CELL("nombrearchivo",A23),FIND(".xlsx",CELL("nombrearchivo",A23))-4,4),2)-RIGHT(YEAR(F24),2))+RIGHT(MID(CELL("nombrearchivo",A23),FIND(".xlsx",CELL("nombrearchivo",A23))-4,4),2)-MONTH(F24)>E24,0,1)) -> 0 | H24: =SUMIFS(CAJA!D:D,CAJA!G:G,"VARIO",CAJA!H:H,"PAGO*",CAJA!B:B,A24) -> 0 | I24: =G24-H24 -> 0 | J24: =IF(I24>D24,"MOROSO",IF(I24>0,"COBRAR CUOTA","NORMAL")) -> NORMAL
G25: =B25+D25*(IF(12*(+LEFT(MID(CELL("nombrearchivo",A24),FIND(".xlsx",CELL("nombrearchivo",A24))-4,4),2)-RIGHT(YEAR(F25),2))+RIGHT(MID(CELL("nombrearchivo",A24),FIND(".xlsx",CELL("nombrearchivo",A24))-4,4),2)-MONTH(F25)>E25,0,1)) -> 0 | H25: =SUMIFS(CAJA!D:D,CAJA!G:G,"VARIO",CAJA!H:H,"PAGO*",CAJA!B:B,A25) -> 0 | I25: =G25-H25 -> 0 | J25: =IF(I25>D25,"MOROSO",IF(I25>0,"COBRAR CUOTA","NORMAL")) -> NORMAL
G26: =B26+D26*(IF(12*(+LEFT(MID(CELL("nombrearchivo",A25),FIND(".xlsx",CELL("nombrearchivo",A25))-4,4),2)-RIGHT(YEAR(F26),2))+RIGHT(MID(CELL("nombrearchivo",A25),FIND(".xlsx",CELL("nombrearchivo",A25))-4,4),2)-MONTH(F26)>E26,0,1)) -> 0 | H26: =SUMIFS(CAJA!D:D,CAJA!G:G,"VARIO",CAJA!H:H,"PAGO*",CAJA!B:B,A26) -> 0 | I26: =G26-H26 -> 0 | J26: =IF(I26>D26,"MOROSO",IF(I26>0,"COBRAR CUOTA","NORMAL")) -> NORMAL
... G29: =B29+D29*(IF(12*(+LEFT(MID(CELL("nombrearchivo",A28),FIND(".xlsx",CELL("nombrearchivo",A28))-4,4),2)-RIGHT(YEAR(F29),2))+RIGHT(MID(CELL("nombrearchivo",A28),FIND(".xlsx",CELL("nombrearchivo",A28))-4,4),2)-MONTH(F29)>E29,0,1)) -> 0 | H29: =SUMIFS(CAJA!D:D,CAJA!G:G,"VARIO",CAJA!H:H,"PAGO*",CAJA!B:B,A29) -> 0 | I29: =G29-H29 -> 0 | J29: =IF(I29>D29,"MOROSO",IF(I29>0,"COBRAR CUOTA","NORMAL")) -> NORMAL

Sheet Saldos
A1: =IF(D1="",TODAY(),D1) -> 45918 | B1: Actual | C1: Inicial
A2: EFE | B2: =SUMIFS(CAJA!D:D,CAJA!I:I,"CAJA",CAJA!J:J,A2,CAJA!A:A,"<=" & A1)-SUMIFS(CAJA!E:E,CAJA!I:I,"CAJA",CAJA!J:J,A2,CAJA!A:A,"<=" & A1)+C2 -> 446255.87 | C2: 1625077.9
A3: CHE | B3: =SUMIFS(CAJA!D:D,CAJA!J:J,A3,CAJA!A:A,"<=" & $A$1)-SUMIFS(CAJA!E:E,CAJA!J:J,A3,CAJA!A:A,"<=" & $A$1)+C3 -> 0
A4: CC | B4: =SUMIFS(CAJA!D:D,CAJA!J:J,A4,CAJA!A:A,"<=" & $A$1)-SUMIFS(CAJA!D:D,CAJA!G:G,"VARIO",CAJA!H:H,"PAGOCC",CAJA!A:A,"<=" & $A$1)+C4 -> 0
A5: MEN | B5: =SUMIFS(CAJA!D:D,CAJA!I:I,A5,CAJA!A:A,"<=" & $A$1)-SUMIFS(CAJA!D:D,CAJA!G:G,"VARIO",CAJA!H:H,"PAGOMEN",CAJA!A:A,"<=" & $A$1)+C5 -> 0
A6: TDC | B6: =SUMIFS(CAJA!D:D,CAJA!J:J,A6,CAJA!A:A,"<=" & $A$1)-SUMIFS(CAJA!E:E,CAJA!J:J,A6,CAJA!A:A,"<=" & $A$1)+C6 -> 0
A7: Caja | B7: =SUMIFS(CAJA!D:D,CAJA!G:G,"ACCESORIO",CAJA!A:A,"=" & $D$8) -> 0 | D7: 43019
A8: CajaAcc | B8: =SUMIFS(CajaAcc!D:D,CajaAcc!A:A,"=" & $D$7) -> 0 | D8: 43019
A9: V24 | B9: =SUMIFS(CAJA!D:D,CAJA!G:G,A9,CAJA!A:A,"<=" & $A$1)-SUMIFS(CAJA!E:E,CAJA!G:G,A9,CAJA!A:A,"<=" & $A$1)+C9 -> 0
A10: Orga | B10: =SUMIFS(CAJA!D:D,CAJA!G:G,A10,CAJA!A:A,"<=" & $A$1)-SUMIFS(CAJA!E:E,CAJA!G:G,A10,CAJA!A:A,"<=" & $A$1)+C10 -> 660

Sheet Gastos
A1: GASTO | B1: =SUMIF(CAJA!$G$4:$G$2485,"GASTO",CAJA!$E$4:$E$2485) -> 2459989.1 | C1: Presupuesto | D1: Control
A2: ALQUILER | B2: =SUMIFS(CAJA!$E$4:$E$2485,CAJA!$G$4:$G$2485,"GASTO",CAJA!$H$4:$H$2485,A2) -> 0 | D2: =IF(C2<B2,"EXCEDIDO","")
A3: AUTOMOTOR | B3: =SUMIFS(CAJA!$E$4:$E$2485,CAJA!$G$4:$G$2485,"GASTO",CAJA!$H$4:$H$2485,A3) -> 0 | D3: =IF(C3<B3,"EXCEDIDO","")
A4: BANCARIOS | B4: =SUMIFS(CAJA!$E$4:$E$2485,CAJA!$G$4:$G$2485,"GASTO",CAJA!$H$4:$H$2485,A4) -> 0 | D4: =IF(C4<B4,"EXCEDIDO","")
A5: COMISION | B5: =SUMIFS(CAJA!$E$4:$E$2485,CAJA!$G$4:$G$2485,"GASTO",CAJA!$H$4:$H$2485,A5) -> -9350 | D5: =IF(C5<B5,"EXCEDIDO","")
A6: FLETE | B6: =SUMIFS(CAJA!$E$4:$E$2485,CAJA!$G$4:$G$2485,"GASTO",CAJA!$H$4:$H$2485,A6) -> 0 | D6: =IF(C6<B6,"EXCEDIDO","")
A7: SERVICIOS | B7: =SUMIFS(CAJA!$E$4:$E$2485,CAJA!$G$4:$G$2485,"GASTO",CAJA!$H$4:$H$2485,A7) -> 208823.77 | D7: =IF(C7<B7,"EXCEDIDO","") -> EXCEDIDO
A8: LIBRERÍA | B8: =SUMIFS(CAJA!$E$4:$E$2485,CAJA!$G$4:$G$2485,"GASTO",CAJA!$H$4:$H$2485,A8) -> 0 | D8: =IF(C8<B8,"EXCEDIDO","")
A9: LIMPIEZA | B9: =SUMIFS(CAJA!$E$4:$E$2485,CAJA!$G$4:$G$2485,"GASTO",CAJA!$H$4:$H$2485,A9) -> 80000 | D9: =IF(C9<B9,"EXCEDIDO","") -> EXCEDIDO
B10: =SUMIFS(CAJA!$E$4:$E$2485,CAJA!$G$4:$G$2485,"GASTO",CAJA!$H$4:$H$2485,A10) -> 0 | D10: =IF(C10<B10,"EXCEDIDO","")
A11: PUBLICIDAD | B11: =SUMIFS(CAJA!$E$4:$E$2485,CAJA!$G$4:$G$2485,"GASTO",CAJA!$H$4:$H$2485,A11) -> 0 | D11: =IF(C11<B11,"EXCEDIDO","")
A12: SUELDOS | B12: =SUMIFS(CAJA!$E$4:$E$2485,CAJA!$G$4:$G$2485,"GASTO",CAJA!$H$4:$H$2485,A12) -> 1425560 | D12: =IF(C12<B12,"EXCEDIDO","") -> EXCEDIDO
B13: =SUMIFS(CAJA!$E$4:$E$2485,CAJA!$G$4:$G$2485,"GASTO",CAJA!$H$4:$H$2485,A13) -> 0 | D13: =IF(C13<B13,"EXCEDIDO","")
A14: VARIOS | B14: =SUMIFS(CAJA!$E$4:$E$2485,CAJA!$G$4:$G$2485,"GASTO",CAJA!$H$4:$H$2485,A14) -> 754955.27 | D14: =IF(C14<B14,"EXCEDIDO","") -> EXCEDIDO
A15: VIATICOS | B15: =SUMIFS(CAJA!$E$4:$E$2485,CAJA!$G$4:$G$2485,"GASTO",CAJA!$H$4:$H$2485,A15) -> 0 | D15: =IF(C15<B15,"EXCEDIDO","")
A16: SEGURIDAD | B16: =SUMIFS(CAJA!$E$4:$E$2485,CAJA!$G$4:$G$2485,"GASTO",CAJA!$H$4:$H$2485,A16) -> 0 | D16: =IF(C16<B16,"EXCEDIDO","")
A17: MUNICIPAL | B17: =SUMIFS(CAJA!$E$4:$E$2485,CAJA!$G$4:$G$2485,"GASTO",CAJA!$H$4:$H$2485,A17) -> 0 | D17: =IF(C17<B17,"EXCEDIDO","")
B18: =SUMIFS(CAJA!$E$4:$E$2485,CAJA!$G$4:$G$2485,"GASTO",CAJA!$H$4:$H$2485,A18) -> 0 | D18: =IF(C18<B18,"EXCEDIDO","")
A19: TOTAL | B19: =SUM(B2:B18) -> 2459989.1 | D19: =IF(C19<B19,"EXCEDIDO","") -> EXCEDIDO
A20: =IF(SUMIF(CAJA!$G$4:$G$2485,"GASTO",CAJA!$D$4:$D$2485)=0,"BIEN","HAY ERRORES") -> BIEN | B20: =IF(ROUND($B$1-$B$19,0)=0,"BIEN","HAY ERRORES") -> BIEN
A21: Ingresos | B21: Validacion

Sheet Equipos
B1: =IF(-SUMIFS(CAJA!F:F,CAJA!G:G,"PROPIO",CAJA!H:H,"<>SIM-CAR")-SUM(B5:B85)+SUM(C5:C85)=0,"BIEN","HAY ERRORES") -> BIEN | C1: =IF(SUMIF(CAJA!$G$4:$G$2485,"HOMO",CAJA!$F$4:$F$2485)-SUM(#REF!)+SUM(#REF!)=0,"HOMOLOGADOS BIEN","HAY ERRORES EN HOMOLOGADOS") -> #REF! | D1: =IF(-SUMIF(CAJA!$G$4:$G$2485,"KIT",CAJA!$F$4:$F$2485)-SUM(D5:D85)+SUM(E5:E85)=0,"BIEN","HAY ERRORES") -> BIEN | E1: =IF(SUMIF(CAJA!$G$4:$G$2485,"HOMO",CAJA!$F$4:$F$2485)-SUM(#REF!)+SUM(#REF!)=0,"HOMOLOGADOS BIEN","HAY ERRORES EN HOMOLOGADOS") -> #REF!
B2: PROPIOS | D2: KITS
A3: Equipo | B3: Actual | C3: Inicial | D3: Actual | E3: Inicial
A4: SIM-CAR | B4: =-SUMIFS(CAJA!$F$4:$F$2485,CAJA!$G$4:$G$2485,"PROPIO",CAJA!$H$4:$H$2485,$A4)-SUMIFS(CAJA!F:F,CAJA!G:G,"?PORTAP")-SUMIFS(CAJA!F:F,CAJA!G:G,"?2G")-SUMIFS(CAJA!F:F,CAJA!G:G,"?4G")-SUMIFS(CAJA!F:F,CAJA!G:G,"?7G")-SUMIFS(CAJA!F:F,CAJA!G:G,"?10G")-SUMIFS(CAJA!F:F,CAJA!G:G,"?20G")-SUMIFS(CAJA!F:F,CAJA!G:G,"?30G")-SUMIFS(CAJA!F:F,CAJA!G:G,"imr")-SUMIFS(CAJA!F:F,CAJA!G:G,"imp")-SUMIFS(CAJA!F:F,CAJA!G:G,"prepaga")-SUMIFS(CAJA!F:F,CAJA!G:G,"portap")+C4 -> 148 | C4: 396 | D4: =-SUMIFS(CAJA!$F$4:$F$2485,CAJA!$G$4:$G$2485,"KIT",CAJA!$H$4:$H$2485,$A4)+E4 -> 0 | F4: =IF(SUM(B4:E4) = 0,"VACIA","")
A5: SIM-1175 | B5: =-SUMIFS(CAJA!$F$4:$F$2485,CAJA!$G$4:$G$2485,"PROPIO",CAJA!$H$4:$H$2485,$A5)+C5 -> 31 | C5: 18 | D5: =-SUMIFS(CAJA!$F$4:$F$2485,CAJA!$G$4:$G$2485,"KIT",CAJA!$H$4:$H$2485,$A5)+E5 -> 0 | F5: =IF(SUM(B5:E5) = 0,"VACIA","")
A6: OBSERVA 3G | B6: =-SUMIFS(CAJA!$F$4:$F$2485,CAJA!$G$4:$G$2485,"PROPIO",CAJA!$H$4:$H$2485,$A6)+C6 -> 0 | C6: 0 | D6: =-SUMIFS(CAJA!$F$4:$F$2485,CAJA!$G$4:$G$2485,"KIT",CAJA!$H$4:$H$2485,$A6)+E6 -> 0 | F6: =IF(SUM(B6:E6) = 0,"VACIA","") -> VACIA
A7: AIO-PBARW18 | B7: =-SUMIFS(CAJA!$F$4:$F$2485,CAJA!$G$4:$G$2485,"PROPIO",CAJA!$H$4:$H$2485,$A7)+C7 -> 0 | C7: 0 | D7: =-SUMIFS(CAJA!$F$4:$F$2485,CAJA!$G$4:$G$2485,"KIT",CAJA!$H$4:$H$2485,$A7)+E7 -> 0 | F7: =IF(SUM(B7:E7) = 0,"VACIA","") -> VACIA
A8: BAT-SL1035PN | B8: =-SUMIFS(CAJA!$F$4:$F$2485,CAJA!$G$4:$G$2485,"PROPIO",CAJA!$H$4:$H$2485,$A8)+C8 -> 0 | C8: 0 | D8: =-SUMIFS(CAJA!$F$4:$F$2485,CAJA!$G$4:$G$2485,"KIT",CAJA!$H$4:$H$2485,$A8)+E8 -> 0 | F8: =IF(SUM(B8:E8) = 0,"VACIA","") -> VACIA
A9: CAM-ECM200W | B9: =-SUMIFS(CAJA!$F$4:$F$2485,CAJA!$G$4:$G$2485,"PROPIO",CAJA!$H$4:$H$2485,$A9)+C9 -> 0 | C9: 0 | D9: =-SUMIFS(CAJA!$F$4:$F$2485,CAJA!$G$4:$G$2485,"KIT",CAJA!$H$4:$H$2485,$A9)+E9 -> 0 | F9: =IF(SUM(B9:E9) = 0,"VACIA","") -> VACIA
A10: CAM-ECMSOL42 | B10: =-SUMIFS(CAJA!$F$4:$F$2485,CAJA!$G$4:$G$2485,"PROPIO",CAJA!$H$4:$H$2485,$A10)+C10 -> 0 | C10: 0 | D10: =-SUMIFS(CAJA!$F$4:$F$2485,CAJA!$G$4:$G$2485,"KIT",CAJA!$H$4:$H$2485,$A10)+E10 -> 0 | F10: =IF(SUM(B10:E10) = 0,"VACIA","") -> VACIA
A11: CAM-EDD053 | B11: =-SUMIFS(CAJA!$F$4:$F$2485,CAJA!$G$4:$G$2485,"PROPIO",CAJA!$H$4:$H$2485,$A11)+C11 -> 0 | C11: 0 | D11: =-SUMIFS(CAJA!$F$4:$F$2485,CAJA!$G$4:$G$2485,"KIT",CAJA!$H$4:$H$2485,$A11)+E11 -> 0 | F11: =IF(SUM(B11:E11) = 0,"VACIA","") -> VACIA
A12: CAM-EDM200W | B12: =-SUMIFS(CAJA!$F$4:$F$2485,CAJA!$G$4:$G$2485,"PROPIO",CAJA!$H$4:$H$2485,$A12)+C12 -> 0 | C12: 0 | D12: =-SUMIFS(CAJA!$F$4:$F$2485,CAJA!$G$4:$G$2485,"KIT",CAJA!$H$4:$H$2485,$A12)+E12 -> 0 | F12: =IF(SUM(B12:E12) = 0,"VACIA","") -> VACIA
A13: CAM-EDM300W | B13: =-SUMIFS(CAJA!$F$4:$F$2485,CAJA!$G$4:$G$2485,"PROPIO",CAJA!$H$4:$H$2485,$A13)+C13 -> 0 | C13: 0 | D13: =-SUMIFS(CAJA!$F$4:$F$2485,CAJA!$G$4:$G$2485,"KIT",CAJA!$H$4:$H$2485,$A13)+E13 -> 0 | F13: =IF(SUM(B13:E13) = 0,"VACIA","") -> VACIA
A14: CAM-FOC518 | B14: =-SUMIFS(CAJA!$F$4:$F$2485,CAJA!$G$4:$G$2485,"PROPIO",CAJA!$H$4:$H$2485,$A14)+C14 -> 0 | C14: 0 | D14: =-SUMIFS(CAJA!$F$4:$F$2485,CAJA!$G$4:$G$2485,"KIT",CAJA!$H$4:$H$2485,$A14)+E14 -> 0 | F14: =IF(SUM(B14:E14) = 0,"VACIA","") -> VACIA
A15: CAM-IROBX90 | B15: =-SUMIFS(CAJA!$F$4:$F$2485,CAJA!$G$4:$G$2485,"PROPIO",CAJA!$H$4:$H$2485,$A15)+C15 -> 0 | C15: 0 | D15: =-SUMIFS(CAJA!$F$4:$F$2485,CAJA!$G$4:$G$2485,"KIT",CAJA!$H$4:$H$2485,$A15)+E15 -> 0 | F15: =IF(SUM(B15:E15) = 0,"VACIA","") -> VACIA
A16: CAM-KT11 | B16: =-SUMIFS(CAJA!$F$4:$F$2485,CAJA!$G$4:$G$2485,"PROPIO",CAJA!$H$4:$H$2485,$A16)+C16 -> 0 | C16: 0 | D16: =-SUMIFS(CAJA!$F$4:$F$2485,CAJA!$G$4:$G$2485,"KIT",CAJA!$H$4:$H$2485,$A16)+E16 -> 0 | F16: =IF(SUM(B16:E16) = 0,"VACIA","") -> VACIA
... A30: NT-LV81WE | B30: =-SUMIFS(CAJA!$F$4:$F$2485,CAJA!$G$4:$G$2485,"PROPIO",CAJA!$H$4:$H$2485,$A30)+C30 -> 0 | C30: 0 | D30: =-SUMIFS(CAJA!$F$4:$F$2485,CAJA!$G$4:$G$2485,"KIT",CAJA!$H$4:$H$2485,$A30)+E30 -> 0 | F30: =IF(SUM(B30:E30) = 0,"VACIA","") -> VACIA
A31: S-A06G128 | B31: =-SUMIFS(CAJA!$F$4:$F$2485,CAJA!$G$4:$G$2485,"PROPIO",CAJA!$H$4:$H$2485,$A31)+C31 -> 3 | C31: 3 | D31: =-SUMIFS(CAJA!$F$4:$F$2485,CAJA!$G$4:$G$2485,"KIT",CAJA!$H$4:$H$2485,$A31)+E31 -> 0 | F31: =IF(SUM(B31:E31) = 0,"VACIA","") | G31: 274999
A32: S-A06G64 | B32: =-SUMIFS(CAJA!$F$4:$F$2485,CAJA!$G$4:$G$2485,"PROPIO",CAJA!$H$4:$H$2485,$A32)+C32 -> 0 | C32: 0 | D32: =-SUMIFS(CAJA!$F$4:$F$2485,CAJA!$G$4:$G$2485,"KIT",CAJA!$H$4:$H$2485,$A32)+E32 -> 0 | F32: =IF(SUM(B32:E32) = 0,"VACIA","") -> VACIA | G32: 389999
A33: S-A14G5 | B33: =-SUMIFS(CAJA!$F$4:$F$2485,CAJA!$G$4:$G$2485,"PROPIO",CAJA!$H$4:$H$2485,$A33)+C33 -> 0 | C33: 0 | D33: =-SUMIFS(CAJA!$F$4:$F$2485,CAJA!$G$4:$G$2485,"KIT",CAJA!$H$4:$H$2485,$A33)+E33 -> 0 | F33: =IF(SUM(B33:E33) = 0,"VACIA","") -> VACIA | G33: 624999
A34: S-A15 | B34: =-SUMIFS(CAJA!$F$4:$F$2485,CAJA!$G$4:$G$2485,"PROPIO",CAJA!$H$4:$H$2485,$A34)+C34 -> 4 | C34: 4 | D34: =-SUMIFS(CAJA!$F$4:$F$2485,CAJA!$G$4:$G$2485,"KIT",CAJA!$H$4:$H$2485,$A34)+E34 -> 0 | F34: =IF(SUM(B34:E34) = 0,"VACIA","") | G34: 389999
A35: S-A16G256 | B35: =-SUMIFS(CAJA!$F$4:$F$2485,CAJA!$G$4:$G$2485,"PROPIO",CAJA!$H$4:$H$2485,$A35)+C35 -> 0 | C35: 0 | D35: =-SUMIFS(CAJA!$F$4:$F$2485,CAJA!$G$4:$G$2485,"KIT",CAJA!$H$4:$H$2485,$A35)+E35 -> 0 | F35: =IF(SUM(B35:E35) = 0,"VACIA","") -> VACIA | G35: 389999
A36: S-A23G5 | B36: =-SUMIFS(CAJA!$F$4:$F$2485,CAJA!$G$4:$G$2485,"PROPIO",CAJA!$H$4:$H$2485,$A36)+C36 -> 1 | C36: 1 | D36: =-SUMIFS(CAJA!$F$4:$F$2485,CAJA!$G$4:$G$2485,"KIT",CAJA!$H$4:$H$2485,$A36)+E36 -> 0 | F36: =IF(SUM(B36:E36) = 0,"VACIA","") | G36: 624999
A37: S-A25 | B37: =-SUMIFS(CAJA!$F$4:$F$2485,CAJA!$G$4:$G$2485,"PROPIO",CAJA!$H$4:$H$2485,$A37)+C37 -> 0 | C37: 0 | D37: =-SUMIFS(CAJA!$F$4:$F$2485,CAJA!$G$4:$G$2485,"KIT",CAJA!$H$4:$H$2485,$A37)+E37 -> 0 | F37: =IF(SUM(B37:E37) = 0,"VACIA","") -> VACIA
A38: S-A26 | B38: =-SUMIFS(CAJA!$F$4:$F$2485,CAJA!$G$4:$G$2485,"PROPIO",CAJA!$H$4:$H$2485,$A38)+C38 -> 0 | C38: 0 | D38: =-SUMIFS(CAJA!$F$4:$F$2485,CAJA!$G$4:$G$2485,"KIT",CAJA!$H$4:$H$2485,$A38)+E38 -> 0 | F38: =IF(SUM(B38:E38) = 0,"VACIA","") -> VACIA
A39: S-A36G2 | B39: =-SUMIFS(CAJA!$F$4:$F$2485,CAJA!$G$4:$G$2485,"PROPIO",CAJA!$H$4:$H$2485,$A39)+C39 -> 0 | C39: 0 | D39: =-SUMIFS(CAJA!$F$4:$F$2485,CAJA!$G$4:$G$2485,"KIT",CAJA!$H$4:$H$2485,$A39)+E39 -> 0 | F39: =IF(SUM(B39:E39) = 0,"VACIA","") -> VACIA
A40: S-M13 | B40: =-SUMIFS(CAJA!$F$4:$F$2485,CAJA!$G$4:$G$2485,"PROPIO",CAJA!$H$4:$H$2485,$A40)+C40 -> 0 | C40: 0 | D40: =-SUMIFS(CAJA!$F$4:$F$2485,CAJA!$G$4:$G$2485,"KIT",CAJA!$H$4:$H$2485,$A40)+E40 -> 0 | F40: =IF(SUM(B40:E40) = 0,"VACIA","") -> VACIA
A41: SM-DT4M | B41: =-SUMIFS(CAJA!$F$4:$F$2485,CAJA!$G$4:$G$2485,"PROPIO",CAJA!$H$4:$H$2485,$A41)+C41 -> 0 | C41: 0 | D41: =-SUMIFS(CAJA!$F$4:$F$2485,CAJA!$G$4:$G$2485,"KIT",CAJA!$H$4:$H$2485,$A41)+E41 -> 0 | F41: =IF(SUM(B41:E41) = 0,"VACIA","") -> VACIA
A42: SM-DT7 | B42: =-SUMIFS(CAJA!$F$4:$F$2485,CAJA!$G$4:$G$2485,"PROPIO",CAJA!$H$4:$H$2485,$A42)+C42 -> 0 | C42: 0 | D42: =-SUMIFS(CAJA!$F$4:$F$2485,CAJA!$G$4:$G$2485,"KIT",CAJA!$H$4:$H$2485,$A42)+E42 -> 0 | F42: =IF(SUM(B42:E42) = 0,"VACIA","") -> VACIA
A43: SM-DT8U | B43: =-SUMIFS(CAJA!$F$4:$F$2485,CAJA!$G$4:$G$2485,"PROPIO",CAJA!$H$4:$H$2485,$A43)+C43 -> 0 | C43: 0 | D43: =-SUMIFS(CAJA!$F$4:$F$2485,CAJA!$G$4:$G$2485,"KIT",CAJA!$H$4:$H$2485,$A43)+E43 -> 0 | F43: =IF(SUM(B43:E43) = 0,"VACIA","") -> VACIA
A44: SM-HWB9 | B44: =-SUMIFS(CAJA!$F$4:$F$2485,CAJA!$G$4:$G$2485,"PROPIO",CAJA!$H$4:$H$2485,$A44)+C44 -> 0 | C44: 0 | D44: =-SUMIFS(CAJA!$F$4:$F$2485,CAJA!$G$4:$G$2485,"KIT",CAJA!$H$4:$H$2485,$A44)+E44 -> 0 | F44: =IF(SUM(B44:E44) = 0,"VACIA","") -> VACIA
A45: SM-SB100 | B45: =-SUMIFS(CAJA!$F$4:$F$2485,CAJA!$G$4:$G$2485,"PROPIO",CAJA!$H$4:$H$2485,$A45)+C45 -> 0 | C45: 0 | D45: =-SUMIFS(CAJA!$F$4:$F$2485,CAJA!$G$4:$G$2485,"KIT",CAJA!$H$4:$H$2485,$A45)+E45 -> 0 | F45: =IF(SUM(B45:E45) = 0,"VACIA","") -> VACIA
A46: SM-SFIR220 | B46: =-SUMIFS(CAJA!$F$4:$F$2485,CAJA!$G$4:$G$2485,"PROPIO",CAJA!$H$4:$H$2485,$A46)+C46 -> 0 | C46: 0 | D46: =-SUMIFS(CAJA!$F$4:$F$2485,CAJA!$G$4:$G$2485,"KIT",CAJA!$H$4:$H$2485,$A46)+E46 -> 0 | F46: =IF(SUM(B46:E46) = 0,"VACIA","") -> VACIA
A47: SM-SM150 | B47: =-SUMIFS(CAJA!$F$4:$F$2485,CAJA!$G$4:$G$2485,"PROPIO",CAJA!$H$4:$H$2485,$A47)+C47 -> 0 | C47: 0 | D47: =-SUMIFS(CAJA!$F$4:$F$2485,CAJA!$G$4:$G$2485,"KIT",CAJA!$H$4:$H$2485,$A47)+E47 -> 0 | F47: =IF(SUM(B47:E47) = 0,"VACIA","") -> VACIA
A48: SM-SR870 | B48: =-SUMIFS(CAJA!$F$4:$F$2485,CAJA!$G$4:$G$2485,"PROPIO",CAJA!$H$4:$H$2485,$A48)+C48 -> 0 | C48: 0 | D48: =-SUMIFS(CAJA!$F$4:$F$2485,CAJA!$G$4:$G$2485,"KIT",CAJA!$H$4:$H$2485,$A48)+E48 -> 0 | F48: =IF(SUM(B48:E48) = 0,"VACIA","") -> VACIA
... A83: ZTE-V50D | B83: =-SUMIFS(CAJA!$F$4:$F$2485,CAJA!$G$4:$G$2485,"PROPIO",CAJA!$H$4:$H$2485,$A83)+C83 -> 0 | C83: 0 | D83: =-SUMIFS(CAJA!$F$4:$F$2485,CAJA!$G$4:$G$2485,"KIT",CAJA!$H$4:$H$2485,$A83)+E83 -> 0 | F83: =IF(SUM(B83:E83) = 0,"VACIA","") -> VACIA
B84: =-SUMIFS(CAJA!$F$4:$F$2485,CAJA!$G$4:$G$2485,"PROPIO",CAJA!$H$4:$H$2485,$A84)+C84 -> 0 | C84: 0 | D84: =-SUMIFS(CAJA!$F$4:$F$2485,CAJA!$G$4:$G$2485,"KIT",CAJA!$H$4:$H$2485,$A84)+E84 -> 0 | F84: =IF(SUM(B84:E84) = 0,"VACIA","") -> VACIA
B85: =-SUMIFS(CAJA!$F$4:$F$2485,CAJA!$G$4:$G$2485,"PROPIO",CAJA!$H$4:$H$2485,$A85)+C85 -> 0 | C85: 0 | D85: =-SUMIFS(CAJA!$F$4:$F$2485,CAJA!$G$4:$G$2485,"KIT",CAJA!$H$4:$H$2485,$A85)+E85 -> 0 | F85: =IF(SUM(B85:E85) = 0,"VACIA","") -> VACIA

Sheet Movimiento
A1: suc??? | B1: --->SUCURSALES
A2: NOMB. CLAVE | B2: ENTIDAD | C2: NOMBRE | D2: CALLE | E2: Nº | F2: P/D | G2: TELEFONO | H2: CIUDAD | I2: CP | J2: PROVINCIA | K2: RESP. | L2: CEL
A3: 1CONCORDIA | B3: 444167 | C3: CONCORDIA | G3: -- | H3: Concordia | I3: 3200 | J3: Entre Rios | K3: Carolina | L3: 3454038245
A4: 1ROJAS | C4: 1ROJAS | D4: 25 de Mayo | E4: 244 | G4: 02475-462592 | H4: Rojas | I4: 2705 | J4: Bs. As. | K4: Carla | L4: 2474465771
A5: 2COLON | C5: 2COLON | D5: Calle 20 | E5: 670 | G5: 02473-430867 | H5: Colon | I5: 2720 | J5: Bs. As. | K5: Monica | L5: 2473508608
A6: 2NICOLAS | B6: 493479 | C6: 2NICOLAS | D6: Mitre | E6: 169 | H6: San Nicolas | I6: 2900 | J6: Bs. As. | K6: Belen | L6: 3364562995
A7: 2ROJAS | C7: 2ROJAS | D7: Irigoyen | E7: 377 | G7: 02475-464827 | H7: Rojas | I7: 2705 | J7: Bs. As. | K7: Joana | L7: 2474494763
A8: 2ROSARIO | B8: -- | C8: 2ROSARIO | D8: San Luis | E8: 1697 | G8: -- | H8: Rosario | I8: 2000 | J8: Santa Fe | K8: Milagros | L8: 3413390134
A9: 3ROSARIO | B9: 505270 | C9: 3ROSARIO | D9: Nanses | E9: 323 | F9: Local 2013 | H9: Rosario | I9: 2000 | J9: Santa Fe | K9: Enzo | L9: 3412765552
A10: 5CORRIENTES | B10: 500089 | C10: CALL | H10: San Nicolas | I10: 2900 | J10: Bs As | K10: Angie | L10: 3412126389
A11: 6CORRIENTES | B11: 540590 | C11: 6CORRIENTES | D11: Catamarca | H11: Corrientes | I11: 3400 | J11: Corrientes | K11: Noelia | L11: 3624524604
A12: ACCESORIOS | B12: -- | C12: ACCESORIOS | D12: Gral. Paz | E12: 1242 | G12: 02477-420856 | H12: Pergamino | I12: 2700 | J12: Bs. As. | K12: Javier | L12: 2477567545
A13: ARRECIFES | C13: ARRECIFES | D13: Ricardo Gutierrez | E13: 656 | G13: 02478-455085 | H13: Arrecifes | I13: 2740 | J13: Bs. As. | L13: 2478519274
A14: CENTENARIO | C14: CENTENARIO | D14: Juan B Justo | E14: 1902 | G14: 02477-445328 | H14: Pergamino | I14: 2700 | J14: Bs. As. | L14: 2477453769
A15: 1CONTABLE | B15: -- | C15: Contable | D15: General Paz | E15: 1240 | G15: 02477-420856 | H15: Pergamino | I15: 2700 | J15: Bs. As. | K15: Eugenia Ferrari | L15: 2477616088
A16: D1175 | C16: D1175 | D16: Rivadavia | E16: 2898 | G16: 011-5779-4293 | H16: C.A.B.A | I16: 1203 | J16: -- | K16: Gabriela | L16: 1160141914
A17: DCEN | C17: Dcen | D17: Gral. Paz | E17: 1242 | G17: 02477-420856 | H17: Pergamino | I17: 2700 | J17: Bs. As. | K17: Luz | L17: 2477-699005
A19: GPAZ | B19: -- | C19: ADMINISTRACION | D19: Gral. Paz | E19: 1242 | G19: 02477-420856 | H19: Pergamino | I19: 2700 | J19: Bs. As. | K19: Eugenia Ferrari | L19: 2477-699005
A21: MERCEDES | B21: 506501 | C21: MERCEDES | D21: San Martin | E21: 897 | H21: Corrientes | I21: 3470 | J21: Corrientes | K21: Paula | L21: 3773451929
A22: PEDRO | C22: PEDRO | D22: Mitre | E22: 970 | G22: 03329-421382 | H22: San Pedro | I22: 2930 | J22: Bs. As. | K22: Victoria | L22: 3329552626
A23: PRODUCTO | B23: -- | C23: PRODUCTO | D23: Gral. Paz | E23: 1242 | G23: 02477-420856 | H23: Pergamino | I23: 2700 | J23: Bs. As. | K23: Eva | L23: 2477329915
A24: SAMBA | B24: -- | C24: Samba | D24: Rivadavia | E24: 2898 | G24: 011-5779-4293 | H24: C.A.B.A | I24: 1203 | J24: -- | K24: Gabriela | L24: 1160141914
A25: SCEN | B25: -- | C25: Scen | D25: Juan B Justo | E25: 1902 | G25: 02477-445328 | H25: Pergamino | I25: 2700 | J25: Bs. As. | K25: Mariana Duarte | L25: 2477489315
A26: SNICOLAS | B26: -- | C26: Snicolas | D26: Nacion | E26: 155 | G26: 03461-434260 | H26: San Nicolas | I26: 2900 | J26: Bs. As. | K26: Eva | L26: 3364495653
A28: PROVEEDOR
A29: CONCILIACION
A30: DISTRIBUCION
A31: REPARACION
A32: GARANTIAS
A33: PROMO
A34: DISCONTINUO
A35: CredicoopO | B35: Banco Credicoop. Cuenta Oslu Cuatro
A36: CredicoopOR | B36: Banco Crediccop. Cuenta Oslu Cuatro Recaudadora
A37: CredicoopC | B37: Banco Credicoop. Cuenta Emar Ceiba
A38: MacroOR | B38: Banco Macro. Cuenta Oslu Cuatro Recaudadora
A39: MacroC | B39: Banco Macro. Cuenta Emar Ceiba
A40: MacroT | B40: Banco Macro. Cuenta Comercializadora TEM
A41: SantanderOR | B41: Banco Santander. Cuenta Oslu Cuatro Recaudadora
A42: SantanderC | B42: Banco Santander. Cuenta Emar Ceiba
A43: BAF | B43: 400846 | C43: BAF | K43: Diego Laurich
A44: TEM
A45: 1Instaladora | K45: Renso Giannone
A48: --->VENDEDORES (de la sucursal)
A49: MAGUI
A50: LUCILA
A51: ENZO
A52: SHAIEL
A64: --->VENDEDORES (de la sucursal)
A81: x

Sheet Ayuda
A1: Caja
A2: En H1 ingresar el nombre de la sucursal
A3: Modificando B2 (fecha) modifica la fecha del cálculo de efectivo, cheques, men y CC
A4: En J1 va el saldo inicial de efectivo. En J2 el saldo inicial de cheques. En L1 el saldo inicial de CC.
A5: Ingresando a M1 o M2 con el nombre utilizado en la columna detalle del cliente calcula el saldo de men (cuenta corriente del mes en curso) del mismo.
A6: Utilizarlo para en el cierre de mes dejar men en 0.
A8: Equipos propios son los celulares libres y las Sims.

Sheet Val
A1: I2PLAY | B1: CAJA | C1: TRANSFER | D1: EFE | E1: VISA
A2: I3PLAY | B2: MEN | C2: DIFERENCIA | D2: MACRO | E2: MASTER
A3: MANT | B3: CC | C3: PAGOMEN | D3: CREDICOOP | E3: MAESTRO
A4: PORTAP | B4: TDC | C4: PAGOCC | D4: SANTANDER | E4: AMEX
A5: R2G | B5: CLARO | D5: GALICIA | E5: NARANJA
A6: R4G | D6: HSBC | E6: CONSUMAX
A7: R7G | D7: NACION | E7: QR
A8: R10G | D8: PBA
A9: R20G
A10: R30G
A11: P2G
A12: P4G
A13: P7G
A14: P10G
A15: P20G
A16: P30G
A17: ORGA
A18: PREPAGA
A19: CATER
A20: MAVERICK
... A26: BAF

Sheet CajaAcc
A1: FECHA | B1: DETALLE | C1: FAC. | D1: INGRESO | E1: Cant | F1: Código de barras | G1: DEST | H1: MODO | I1: Nº | J1: Movim. | K1: OBSERVACIONES | L1: M/m | M1: Costo sugerido | N1: Descripción
A2: 45809 | B2: Consumidor final | D2: 4500 | E2: 1 | F2: FDT'A346 | G2: caja | H2: efe | J2: Enzo | L2: 5 | M2: =IFERROR(ROUNDUP(VLOOKUP(F2,Accesorio!A:E,IF(L2>5,L2-2,L2),)*E2/IF(L2>5,1.21,1),0)," ") -> 4500 | N2: =IFERROR(VLOOKUP(F2,Accesorio!A:C,3,),"") -> GLASS SAM. A15 / A25 / A34
A3: 45809 | B3: Consumidor final | D3: 5500 | E3: 1 | F3: FD9DG04NE | G3: tdc | H3: qr | J3: Enzo | L3: 5 | M3: =IFERROR(ROUNDUP(VLOOKUP(F3,Accesorio!A:E,IF(L3>5,L3-2,L3),)*E3/IF(L3>5,1.21,1),0)," ") -> 5500 | N3: =IFERROR(VLOOKUP(F3,Accesorio!A:C,3,),"") -> GLASS FULL MOT. G04 / G24
A4: 45809 | B4: Consumidor final | D4: 10000 | E4: 1 | F4: ssfa06 | G4: tdc | H4: visa | I4: 561 | J4: Shaiel | L4: 5 | M4: =IFERROR(ROUNDUP(VLOOKUP(F4,Accesorio!A:E,IF(L4>5,L4-2,L4),)*E4/IF(L4>5,1.21,1),0)," ") -> 10000 | N4: =IFERROR(VLOOKUP(F4,Accesorio!A:C,3,),"") -> TPU SAM. A06 SILICONA FELPA (AAA)
A5: 45809 | B5: Consumidor final | D5: 9500 | E5: 1 | F5: 6952025612635 | G5: tdc | H5: visa | I5: 561 | J5: Shaiel | L5: 5 | M5: =IFERROR(ROUNDUP(VLOOKUP(F5,Accesorio!A:E,IF(L5>5,L5-2,L5),)*E5/IF(L5>5,1.21,1),0)," ") -> 9500 | N5: =IFERROR(VLOOKUP(F5,Accesorio!A:C,3,),"") -> CABLE TIPO C 1MTS 6.0A TREQA
A6: 45809 | B6: Consumidor final | D6: 4500 | E6: 1 | F6: FDT'A54 | G6: tdc | H6: visa | I6: 561 | J6: Shaiel | L6: 5 | M6: =IFERROR(ROUNDUP(VLOOKUP(F6,Accesorio!A:E,IF(L6>5,L6-2,L6),)*E6/IF(L6>5,1.21,1),0)," ") -> 4500 | N6: =IFERROR(VLOOKUP(F6,Accesorio!A:C,3,),"") -> GLASS SAM. A54
A7: 45809 | B7: Consumidor final | D7: 6000 | E7: 1 | F7: FPXR14C | G7: caja | H7: efe | J7: Shaiel | L7: 5 | M7: =IFERROR(ROUNDUP(VLOOKUP(F7,Accesorio!A:E,IF(L7>5,L7-2,L7),)*E7/IF(L7>5,1.21,1),0)," ") -> 6000 | N7: =IFERROR(VLOOKUP(F7,Accesorio!A:C,3,),"") -> TPU XIAOMI REDMI 14C PUFFER IMP.
A8: 45809 | B8: Consumidor final | D8: 7500 | E8: 1 | F8: HG'FILMS | G8: caja | H8: efe | J8: Shaiel | L8: 5 | M8: =IFERROR(ROUNDUP(VLOOKUP(F8,Accesorio!A:E,IF(L8>5,L8-2,L8),)*E8/IF(L8>5,1.21,1),0)," ") -> 7500 | N8: =IFERROR(VLOOKUP(F8,Accesorio!A:C,3,),"") -> HIDROGEL FILMINAS CLEAR 180X120
A9: 45809 | B9: Consumidor final | D9: 14000 | E9: 1 | F9: prpsa35 | G9: tdc | H9: visa | I9: 562 | J9: Shaiel | L9: 5 | M9: =IFERROR(ROUNDUP(VLOOKUP(F9,Accesorio!A:E,IF(L9>5,L9-2,L9),)*E9/IF(L9>5,1.21,1),0)," ") -> 14000 | N9: =IFERROR(VLOOKUP(F9,Accesorio!A:C,3,),"") -> TPU SAM. A35 TRANS CLEAR PREMIUM REF
A10: 45809 | B10: Consumidor final | D10: 5500 | E10: 1 | F10: fd5da35 | G10: tdc | H10: visa | I10: 562 | J10: Shaiel | L10: 5 | M10: =IFERROR(ROUNDUP(VLOOKUP(F10,Accesorio!A:E,IF(L10>5,L10-2,L10),)*E10/IF(L10>5,1.21,1),0)," ") -> 5500 | N10: =IFERROR(VLOOKUP(F10,Accesorio!A:C,3,),"") -> GLASS FULL SAM. A35
A11: 45810 | B11: Consumidor final | D11: 7000 | E11: 1 | F11: GFCEIPH14P | G11: caja | H11: efe | J11: Enzo | L11: 5 | M11: =IFERROR(ROUNDUP(VLOOKUP(F11,Accesorio!A:E,IF(L11>5,L11-2,L11),)*E11/IF(L11>5,1.21,1),0)," ") -> 7000 | N11: =IFERROR(VLOOKUP(F11,Accesorio!A:C,3,),"") -> GLASS CERAMICA IPH 14 PRO - 100D
A12: 45810 | B12: Consumidor final | D12: 7500 | E12: 1 | F12: HG'FILMS | G12: caja | H12: efe | J12: Lucila | L12: 5 | M12: =IFERROR(ROUNDUP(VLOOKUP(F12,Accesorio!A:E,IF(L12>5,L12-2,L12),)*E12/IF(L12>5,1.21,1),0)," ") -> 7500 | N12: =IFERROR(VLOOKUP(F12,Accesorio!A:C,3,),"") -> HIDROGEL FILMINAS CLEAR 180X120
A13: 45810 | B13: Consumidor final | D13: 7500 | E13: 1 | F13: SILFA15 | G13: caja | H13: efe | J13: Enzo | L13: 5 | M13: =IFERROR(ROUNDUP(VLOOKUP(F13,Accesorio!A:E,IF(L13>5,L13-2,L13),)*E13/IF(L13>5,1.21,1),0)," ") -> 7500 | N13: =IFERROR(VLOOKUP(F13,Accesorio!A:C,3,),"") -> TPU SAM. A15 SILICONA FELPA
A14: 45810 | B14: Consumidor final | D14: 7500 | E14: 1 | F14: HG'FILMS | G14: caja | H14: efe | J14: Lucila | L14: 5 | M14: =IFERROR(ROUNDUP(VLOOKUP(F14,Accesorio!A:E,IF(L14>5,L14-2,L14),)*E14/IF(L14>5,1.21,1),0)," ") -> 7500 | N14: =IFERROR(VLOOKUP(F14,Accesorio!A:C,3,),"") -> HIDROGEL FILMINAS CLEAR 180X120
A15: 45812 | B15: Consumidor final | D15: 5500 | E15: 1 | F15: FD5D'A325NE | G15: caja | H15: efe | I15: QR | J15: Enzo | L15: 5 | M15: =IFERROR(ROUNDUP(VLOOKUP(F15,Accesorio!A:E,IF(L15>5,L15-2,L15),)*E15/IF(L15>5,1.21,1),0)," ") -> 5500 | N15: =IFERROR(VLOOKUP(F15,Accesorio!A:C,3,),"") -> GLASS FULL SAM. A32
A16: 45812 | B16: Consumidor final | D16: 5000 | E16: 1 | F16: 6940351172855 | G16: caja | H16: efe | I16: QR | J16: Enzo | L16: 5 | M16: =IFERROR(ROUNDUP(VLOOKUP(F16,Accesorio!A:E,IF(L16>5,L16-2,L16),)*E16/IF(L16>5,1.21,1),0)," ") -> 5000 | N16: =IFERROR(VLOOKUP(F16,Accesorio!A:C,3,),"") -> CABLE MICRO 1MTS KOSMO
A17: 45812 | B17: Consumidor final | D17: 7500 | E17: 1 | F17: HG'FILMS | G17: caja | H17: efe | J17: Shaiel | L17: 5 | M17: =IFERROR(ROUNDUP(VLOOKUP(F17,Accesorio!A:E,IF(L17>5,L17-2,L17),)*E17/IF(L17>5,1.21,1),0)," ") -> 7500 | N17: =IFERROR(VLOOKUP(F17,Accesorio!A:C,3,),"") -> HIDROGEL FILMINAS CLEAR 180X120
A18: 45812 | B18: Consumidor final | D18: 5500 | E18: 1 | F18: FD5ME15 | G18: caja | H18: efe | J18: Enzo | L18: 5 | M18: =IFERROR(ROUNDUP(VLOOKUP(F18,Accesorio!A:E,IF(L18>5,L18-2,L18),)*E18/IF(L18>5,1.21,1),0)," ") -> 5500 | N18: =IFERROR(VLOOKUP(F18,Accesorio!A:C,3,),"") -> GLASS FULL MOT. G05 / E15
A19: 45813 | B19: Consumidor final | D19: 4500 | E19: 1 | F19: FDT'G14 | G19: caja | H19: efe | J19: Shaiel | L19: 5 | M19: =IFERROR(ROUNDUP(VLOOKUP(F19,Accesorio!A:E,IF(L19>5,L19-2,L19),)*E19/IF(L19>5,1.21,1),0)," ") -> 4500 | N19: =IFERROR(VLOOKUP(F19,Accesorio!A:C,3,),"") -> GLASS MOT. G14
A20: 45813 | B20: Consumidor final | D20: 7500 | E20: 1 | F20: HG'FILMS | G20: tdc | H20: visa | I20: 563 | J20: Shaiel | L20: 5 | M20: =IFERROR(ROUNDUP(VLOOKUP(F20,Accesorio!A:E,IF(L20>5,L20-2,L20),)*E20/IF(L20>5,1.21,1),0)," ") -> 7500 | N20: =IFERROR(VLOOKUP(F20,Accesorio!A:C,3,),"") -> HIDROGEL FILMINAS CLEAR 180X120
A21: 45815 | B21: Consumidor final | D21: 5000 | E21: 1 | F21: 215024 | G21: tdc | H21: visa | I21: 564 | J21: Shaiel | L21: 5 | M21: =IFERROR(ROUNDUP(VLOOKUP(F21,Accesorio!A:E,IF(L21>5,L21-2,L21),)*E21/IF(L21>5,1.21,1),0)," ") -> 5000 | N21: =IFERROR(VLOOKUP(F21,Accesorio!A:C,3,),"") -> TPU SAM. A24 TRANS
A22: 45815 | B22: Consumidor final | D22: 5500 | E22: 1 | F22: 4715001120 | G22: tdc | H22: visa | I22: 564 | J22: Shaiel | L22: 5 | M22: =IFERROR(ROUNDUP(VLOOKUP(F22,Accesorio!A:E,IF(L22>5,L22-2,L22),)*E22/IF(L22>5,1.21,1),0)," ") -> 5500 | N22: =IFERROR(VLOOKUP(F22,Accesorio!A:C,3,),"") -> CAR. PARED CABEZAL USB - 2A KOSMO
A23: 45815 | B23: Consumidor final | D23: 5500 | E23: 1 | F23: FD5MG15 | G23: caja | H23: efe | J23: Shaiel | L23: 5 | M23: =IFERROR(ROUNDUP(VLOOKUP(F23,Accesorio!A:E,IF(L23>5,L23-2,L23),)*E23/IF(L23>5,1.21,1),0)," ") -> 5500 | N23: =IFERROR(VLOOKUP(F23,Accesorio!A:C,3,),"") -> GLASS FULL MOT. G15
A24: 45815 | B24: Consumidor final | D24: 7500 | E24: 1 | F24: SILFA15 | G24: caja | H24: efe | J24: Shaiel | L24: 5 | M24: =IFERROR(ROUNDUP(VLOOKUP(F24,Accesorio!A:E,IF(L24>5,L24-2,L24),)*E24/IF(L24>5,1.21,1),0)," ") -> 7500 | N24: =IFERROR(VLOOKUP(F24,Accesorio!A:C,3,),"") -> TPU SAM. A15 SILICONA FELPA
A25: 45815 | B25: Consumidor final | D25: 5000 | E25: 1 | F25: 21A15TR | G25: caja | H25: efe | J25: Shaiel | L25: 5 | M25: =IFERROR(ROUNDUP(VLOOKUP(F25,Accesorio!A:E,IF(L25>5,L25-2,L25),)*E25/IF(L25>5,1.21,1),0)," ") -> 5000 | N25: =IFERROR(VLOOKUP(F25,Accesorio!A:C,3,),"") -> TPU SAM. A15 TRANS
A26: 45815 | B26: Consumidor final | D26: 11000 | E26: 1 | F26: puIP1439B | G26: caja | H26: efe | J26: Shaiel | L26: 5 | M26: =IFERROR(ROUNDUP(VLOOKUP(F26,Accesorio!A:E,IF(L26>5,L26-2,L26),)*E26/IF(L26>5,1.21,1),0)," ") -> 11000 | N26: =IFERROR(VLOOKUP(F26,Accesorio!A:C,3,),"") -> TPU IPH 14 / 13 BORDER COLOR
A27: 45815 | B27: Consumidor final | D27: 32000 | E27: 1 | F27: 194252192399 | G27: caja | H27: efe | I27: QR | J27: Shaiel | L27: 5 | M27: =IFERROR(ROUNDUP(VLOOKUP(F27,Accesorio!A:E,IF(L27>5,L27-2,L27),)*E27/IF(L27>5,1.21,1),0)," ") -> 32000 | N27: =IFERROR(VLOOKUP(F27,Accesorio!A:C,3,),"") -> CAR. INALAMBRICO MAGNETICO USB-C APPLE A2140
A28: 45816 | B28: Consumidor final | D28: 4500 | E28: 1 | F28: fdt'g84 | G28: caja | H28: efe | J28: Shaiel | L28: 5 | M28: =IFERROR(ROUNDUP(VLOOKUP(F28,Accesorio!A:E,IF(L28>5,L28-2,L28),)*E28/IF(L28>5,1.21,1),0)," ") -> 4500 | N28: =IFERROR(VLOOKUP(F28,Accesorio!A:C,3,),"") -> GLASS MOT. G84
A29: 45816 | B29: Consumidor final | D29: 7500 | E29: 1 | F29: puDFA15 | G29: caja | H29: efe | J29: Shaiel | L29: 5 | M29: =IFERROR(ROUNDUP(VLOOKUP(F29,Accesorio!A:E,IF(L29>5,L29-2,L29),)*E29/IF(L29>5,1.21,1),0)," ") -> 7500 | N29: =IFERROR(VLOOKUP(F29,Accesorio!A:C,3,),"") -> TPU SAM. A15 BORDER DIFUMADO REF
A30: 45816 | B30: Consumidor final | D30: 8500 | E30: 1 | F30: TPIPIH12PDIR | G30: tdc | H30: visa | I30: 568 | J30: Lucila | L30: 5 | M30: =IFERROR(ROUNDUP(VLOOKUP(F30,Accesorio!A:E,IF(L30>5,L30-2,L30),)*E30/IF(L30>5,1.21,1),0)," ") -> 8500 | N30: =IFERROR(VLOOKUP(F30,Accesorio!A:C,3,),"") -> TPU IPH 12 / 12 PRO DIAMON
A31: 45816 | B31: Consumidor final | D31: 7500 | E31: 1 | F31: PUdfa15 | G31: tdc | H31: visa | I31: 568 | J31: Lucila | L31: 5 | M31: =IFERROR(ROUNDUP(VLOOKUP(F31,Accesorio!A:E,IF(L31>5,L31-2,L31),)*E31/IF(L31>5,1.21,1),0)," ") -> 7500 | N31: =IFERROR(VLOOKUP(F31,Accesorio!A:C,3,),"") -> TPU SAM. A15 BORDER DIFUMADO REF
A32: 45816 | B32: Consumidor final | D32: 7000 | E32: 1 | F32: gfcesa15 | G32: tdc | H32: visa | I32: 568 | J32: Lucila | L32: 5 | M32: =IFERROR(ROUNDUP(VLOOKUP(F32,Accesorio!A:E,IF(L32>5,L32-2,L32),)*E32/IF(L32>5,1.21,1),0)," ") -> 7000 | N32: =IFERROR(VLOOKUP(F32,Accesorio!A:C,3,),"") -> GLASS CERAMICA SAM. A15 / A25 / A34 100D
A33: 45816 | B33: Consumidor final | D33: 4500 | E33: 1 | F33: FDT'A04E | G33: caja | H33: efe | J33: Lucila | L33: 5 | M33: =IFERROR(ROUNDUP(VLOOKUP(F33,Accesorio!A:E,IF(L33>5,L33-2,L33),)*E33/IF(L33>5,1.21,1),0)," ") -> 4500 | N33: =IFERROR(VLOOKUP(F33,Accesorio!A:C,3,),"") -> GLASS SAM. A04 /A04S / A04E
A34: 45816 | B34: Consumidor final | D34: 15500 | E34: 1 | F34: tcra15 | G34: tdc | H34: master | I34: 559 | J34: Lucila | L34: 5 | M34: =IFERROR(ROUNDUP(VLOOKUP(F34,Accesorio!A:E,IF(L34>5,L34-2,L34),)*E34/IF(L34>5,1.21,1),0)," ") -> 15500 | N34: =IFERROR(VLOOKUP(F34,Accesorio!A:C,3,),"") -> TPU SAM. A15 / A25 CUERO
A35: 45817 | B35: Consumidor final | D35: 9500 | E35: 1 | F35: PRBMCI16P | G35: caja | H35: efe | J35: Enzo | L35: 5 | M35: =IFERROR(ROUNDUP(VLOOKUP(F35,Accesorio!A:E,IF(L35>5,L35-2,L35),)*E35/IF(L35>5,1.21,1),0)," ") -> 9500 | N35: =IFERROR(VLOOKUP(F35,Accesorio!A:C,3,),"") -> TPU IPH 16 PRO MAGNETICO TRANS COLOR
A36: 45817 | B36: Consumidor final | D36: 4500 | E36: 1 | F36: 11A21 | G36: caja | H36: efe | J36: Enzo | L36: 5 | M36: =IFERROR(ROUNDUP(VLOOKUP(F36,Accesorio!A:E,IF(L36>5,L36-2,L36),)*E36/IF(L36>5,1.21,1),0)," ") -> 4500 | N36: =IFERROR(VLOOKUP(F36,Accesorio!A:C,3,),"") -> TPU MOT. G22/E32 NAC. LISO
A37: 45817 | B37: Consumidor final | D37: 7500 | E37: 1 | F37: 714604205876 | G37: caja | H37: efe | J37: Enzo | L37: 5 | M37: =IFERROR(ROUNDUP(VLOOKUP(F37,Accesorio!A:E,IF(L37>5,L37-2,L37),)*E37/IF(L37>5,1.21,1),0)," ") -> 7500 | N37: =IFERROR(VLOOKUP(F37,Accesorio!A:C,3,),"") -> CAR. PARED TIPO C 2.75A - USB+CABLE KOSMO
A38: 45817 | B38: Consumidor final | D38: 4500 | E38: 1 | F38: FDT'XT2235 | G38: caja | H38: efe | J38: Enzo | L38: 5 | M38: =IFERROR(ROUNDUP(VLOOKUP(F38,Accesorio!A:E,IF(L38>5,L38-2,L38),)*E38/IF(L38>5,1.21,1),0)," ") -> 4500 | N38: =IFERROR(VLOOKUP(F38,Accesorio!A:C,3,),"") -> GLASS MOT. G32
A39: 45817 | B39: Consumidor final | D39: 7500 | E39: 1 | F39: PUdfa15 | G39: caja | H39: efe | J39: Enzo | L39: 5 | M39: =IFERROR(ROUNDUP(VLOOKUP(F39,Accesorio!A:E,IF(L39>5,L39-2,L39),)*E39/IF(L39>5,1.21,1),0)," ") -> 7500 | N39: =IFERROR(VLOOKUP(F39,Accesorio!A:C,3,),"") -> TPU SAM. A15 BORDER DIFUMADO REF
A40: 45819 | B40: Grimao, Shaiel | D40: 1369 | E40: 1 | F40: 6952024615682 | G40: caja | H40: efe | J40: Shaiel | L40: 4 | M40: =IFERROR(ROUNDUP(VLOOKUP(F40,Accesorio!A:E,IF(L40>5,L40-2,L40),)*E40/IF(L40>5,1.21,1),0)," ") -> 1369 | N40: =IFERROR(VLOOKUP(F40,Accesorio!A:C,3,),"") -> CABLE MICRO 1MTS TREQA 6A CA-8641
A41: 45819 | B41: Grimao, Shaiel | D41: 7357 | E41: 1 | F41: 190199040670 | G41: caja | H41: efe | J41: Shaiel | L41: 4 | M41: =IFERROR(ROUNDUP(VLOOKUP(F41,Accesorio!A:E,IF(L41>5,L41-2,L41),)*E41/IF(L41>5,1.21,1),0)," ") -> 6042 | N41: =IFERROR(VLOOKUP(F41,Accesorio!A:C,3,),"") -> CAR. PARED CABEZAL USB-C - 20W 3A KOSMIC
A42: 45819 | B42: Consumidor final | D42: 7500 | E42: 1 | F42: HG'FILMS | G42: caja | H42: efe | J42: Enzo | L42: 5 | M42: =IFERROR(ROUNDUP(VLOOKUP(F42,Accesorio!A:E,IF(L42>5,L42-2,L42),)*E42/IF(L42>5,1.21,1),0)," ") -> 7500 | N42: =IFERROR(VLOOKUP(F42,Accesorio!A:C,3,),"") -> HIDROGEL FILMINAS CLEAR 180X120
A43: 45820 | B43: Consumidor final | D43: 5500 | E43: 1 | F43: FD5DG75 | G43: tdc | H43: naranja | I43: 570 | J43: Shaiel | L43: 5 | M43: =IFERROR(ROUNDUP(VLOOKUP(F43,Accesorio!A:E,IF(L43>5,L43-2,L43),)*E43/IF(L43>5,1.21,1),0)," ") -> 5500 | N43: =IFERROR(VLOOKUP(F43,Accesorio!A:C,3,),"") -> GLASS FULL MOT. G75
A44: 45820 | B44: Consumidor final | D44: 5000 | E44: 1 | F44: 21G85TR | G44: tdc | H44: naranja | I44: 570 | J44: Shaiel | L44: 5 | M44: =IFERROR(ROUNDUP(VLOOKUP(F44,Accesorio!A:E,IF(L44>5,L44-2,L44),)*E44/IF(L44>5,1.21,1),0)," ") -> 5000 | N44: =IFERROR(VLOOKUP(F44,Accesorio!A:C,3,),"") -> TPU MOT. G85 TRANS
A45: 45820 | B45: Consumidor final | D45: 5500 | E45: 1 | F45: FD5D'IPH13PMNE | G45: caja | H45: efe | J45: Shaiel | L45: 5 | M45: =IFERROR(ROUNDUP(VLOOKUP(F45,Accesorio!A:E,IF(L45>5,L45-2,L45),)*E45/IF(L45>5,1.21,1),0)," ") -> 5500 | N45: =IFERROR(VLOOKUP(F45,Accesorio!A:C,3,),"") -> GLASS FULL IPH 13 PRO MAX
A46: 45821 | B46: Consumidor final | D46: 5500 | E46: 1 | F46: fd5dg75 | G46: caja | H46: efe | J46: Enzo | L46: 5 | M46: =IFERROR(ROUNDUP(VLOOKUP(F46,Accesorio!A:E,IF(L46>5,L46-2,L46),)*E46/IF(L46>5,1.21,1),0)," ") -> 5500 | N46: =IFERROR(VLOOKUP(F46,Accesorio!A:C,3,),"") -> GLASS FULL MOT. G75
A47: 45822 | B47: Consumidor final | D47: 6500 | E47: 1 | F47: 21A06TR | G47: caja | H47: efe | J47: Lucila | L47: 5 | M47: =IFERROR(ROUNDUP(VLOOKUP(F47,Accesorio!A:E,IF(L47>5,L47-2,L47),)*E47/IF(L47>5,1.21,1),0)," ") -> 6500 | N47: =IFERROR(VLOOKUP(F47,Accesorio!A:C,3,),"") -> TPU SAM. A06 TRANS
A48: 45822 | B48: Consumidor final | D48: 5500 | E48: 1 | F48: GFPIPH13PM | G48: caja | H48: efe | J48: Lucila | L48: 5 | M48: =IFERROR(ROUNDUP(VLOOKUP(F48,Accesorio!A:E,IF(L48>5,L48-2,L48),)*E48/IF(L48>5,1.21,1),0)," ") -> 5500 | N48: =IFERROR(VLOOKUP(F48,Accesorio!A:C,3,),"") -> GLASS FULL IPH 13 PRO MAX PRIVACY
A49: 45822 | B49: Consumidor final | D49: 7500 | E49: 1 | F49: SILFBMG04 | G49: caja | H49: efe | J49: Lucila | L49: 5 | M49: =IFERROR(ROUNDUP(VLOOKUP(F49,Accesorio!A:E,IF(L49>5,L49-2,L49),)*E49/IF(L49>5,1.21,1),0)," ") -> 7500 | N49: =IFERROR(VLOOKUP(F49,Accesorio!A:C,3,),"") -> TPU MOT. E14 / G04 / G04S / G24 / G24 POWER SILICONA FELPA BRILLO
A50: 45822 | B50: Consumidor final | D50: 9500 | E50: 1 | F50: silfg75 | G50: caja | H50: efe | J50: Shaiel | L50: 5 | M50: =IFERROR(ROUNDUP(VLOOKUP(F50,Accesorio!A:E,IF(L50>5,L50-2,L50),)*E50/IF(L50>5,1.21,1),0)," ") -> 9500 | N50: =IFERROR(VLOOKUP(F50,Accesorio!A:C,3,),"") -> TPU MOT. G75 SILICONA FELPA
A51: 45822 | B51: Consumidor final | D51: 5000 | E51: 1 | F51: 21A15TR | G51: tdc | H51: visa | I51: 571 | J51: Shaiel | L51: 5 | M51: =IFERROR(ROUNDUP(VLOOKUP(F51,Accesorio!A:E,IF(L51>5,L51-2,L51),)*E51/IF(L51>5,1.21,1),0)," ") -> 5000 | N51: =IFERROR(VLOOKUP(F51,Accesorio!A:C,3,),"") -> TPU SAM. A15 TRANS
A52: 45822 | B52: Consumidor final | D52: 5500 | E52: 1 | F52: fd5mg15 | G52: caja | H52: efe | J52: Shaiel | L52: 5 | M52: =IFERROR(ROUNDUP(VLOOKUP(F52,Accesorio!A:E,IF(L52>5,L52-2,L52),)*E52/IF(L52>5,1.21,1),0)," ") -> 5500 | N52: =IFERROR(VLOOKUP(F52,Accesorio!A:C,3,),"") -> GLASS FULL MOT. G15
A53: 45822 | B53: Consumidor final | D53: 8000 | E53: 1 | F53: fd5d'xt2421 | G53: caja | H53: efe | J53: Shaiel | L53: 5 | M53: =IFERROR(ROUNDUP(VLOOKUP(F53,Accesorio!A:E,IF(L53>5,L53-2,L53),)*E53/IF(L53>5,1.21,1),0)," ") -> 8000 | N53: =IFERROR(VLOOKUP(F53,Accesorio!A:C,3,),"") -> GLASS FULL MOT. E14
A54: 45822 | B54: Consumidor final | D54: 11000 | E54: 1 | F54: FCUS'UNI55NE | G54: tdc | H54: visa | I54: 572 | J54: Shaiel | L54: 5 | M54: =IFERROR(ROUNDUP(VLOOKUP(F54,Accesorio!A:E,IF(L54>5,L54-2,L54),)*E54/IF(L54>5,1.21,1),0)," ") -> 11000 | N54: =IFERROR(VLOOKUP(F54,Accesorio!A:C,3,),"") -> FLIP UNI. 5,5" SILICONA NEGRO
A55: 45822 | B55: Consumidor final | D55: 7500 | E55: 1 | F55: HG'FILMS | G55: tdc | H55: visa | I55: 572 | J55: Shaiel | L55: 5 | M55: =IFERROR(ROUNDUP(VLOOKUP(F55,Accesorio!A:E,IF(L55>5,L55-2,L55),)*E55/IF(L55>5,1.21,1),0)," ") -> 7500 | N55: =IFERROR(VLOOKUP(F55,Accesorio!A:C,3,),"") -> HIDROGEL FILMINAS CLEAR 180X120
A56: 45822 | B56: Consumidor final | D56: 9500 | E56: 1 | F56: silfg05 | G56: tdc | H56: visa | I56: 573 | J56: Shaiel | L56: 5 | M56: =IFERROR(ROUNDUP(VLOOKUP(F56,Accesorio!A:E,IF(L56>5,L56-2,L56),)*E56/IF(L56>5,1.21,1),0)," ") -> 9500 | N56: =IFERROR(VLOOKUP(F56,Accesorio!A:C,3,),"") -> TPU MOT. G05 / E15 SILICONA FELPA
A57: 45822 | B57: Consumidor final | D57: 5500 | E57: 1 | F57: fd5me15 | G57: tdc | H57: visa | I57: 573 | J57: Shaiel | L57: 5 | M57: =IFERROR(ROUNDUP(VLOOKUP(F57,Accesorio!A:E,IF(L57>5,L57-2,L57),)*E57/IF(L57>5,1.21,1),0)," ") -> 5500 | N57: =IFERROR(VLOOKUP(F57,Accesorio!A:C,3,),"") -> GLASS FULL MOT. G05 / E15
A58: 45823 | B58: Consumidor final | D58: 8500 | E58: 1 | F58: TPIPIH11DIR | G58: caja | H58: efe | J58: Enzo | L58: 5 | M58: =IFERROR(ROUNDUP(VLOOKUP(F58,Accesorio!A:E,IF(L58>5,L58-2,L58),)*E58/IF(L58>5,1.21,1),0)," ") -> 8500 | N58: =IFERROR(VLOOKUP(F58,Accesorio!A:C,3,),"") -> TPU IPH 11 / XR DIAMON
A59: 45823 | B59: Consumidor final | D59: 8000 | E59: 1 | F59: 16133 | G59: caja | H59: efe | J59: Enzo | L59: 5 | M59: =IFERROR(ROUNDUP(VLOOKUP(F59,Accesorio!A:E,IF(L59>5,L59-2,L59),)*E59/IF(L59>5,1.21,1),0)," ") -> 8000 | N59: =IFERROR(VLOOKUP(F59,Accesorio!A:C,3,),"") -> TPU IPH 14 / 13 PUFFER IMP.
A60: 45823 | B60: Consumidor final | D60: 4500 | E60: 1 | F60: 40322 | G60: caja | H60: efe | J60: Enzo | L60: 5 | M60: =IFERROR(ROUNDUP(VLOOKUP(F60,Accesorio!A:E,IF(L60>5,L60-2,L60),)*E60/IF(L60>5,1.21,1),0)," ") -> 4500 | N60: =IFERROR(VLOOKUP(F60,Accesorio!A:C,3,),"") -> TPU SAM. A33 PUFFER CASE
A61: 45823 | B61: Consumidor final | D61: 11500 | E61: 1 | F61: SILFIPH14 | G61: caja | H61: efe | J61: Enzo | L61: 5 | M61: =IFERROR(ROUNDUP(VLOOKUP(F61,Accesorio!A:E,IF(L61>5,L61-2,L61),)*E61/IF(L61>5,1.21,1),0)," ") -> 11500 | N61: =IFERROR(VLOOKUP(F61,Accesorio!A:C,3,),"") -> TPU IPH 14 / 13 SILICONA FELPA
A62: 45823 | B62: Consumidor final | D62: 7500 | E62: 1 | F62: HG'FILMS | G62: caja | H62: efe | J62: Shaiel | L62: 5 | M62: =IFERROR(ROUNDUP(VLOOKUP(F62,Accesorio!A:E,IF(L62>5,L62-2,L62),)*E62/IF(L62>5,1.21,1),0)," ") -> 7500 | N62: =IFERROR(VLOOKUP(F62,Accesorio!A:C,3,),"") -> HIDROGEL FILMINAS CLEAR 180X120
A63: 45823 | B63: Consumidor final | D63: 7500 | E63: 1 | F63: HG'FILMS | G63: caja | H63: efe | J63: Shaiel | L63: 5 | M63: =IFERROR(ROUNDUP(VLOOKUP(F63,Accesorio!A:E,IF(L63>5,L63-2,L63),)*E63/IF(L63>5,1.21,1),0)," ") -> 7500 | N63: =IFERROR(VLOOKUP(F63,Accesorio!A:C,3,),"") -> HIDROGEL FILMINAS CLEAR 180X120
A64: 45823 | B64: Consumidor final | D64: 12000 | E64: 1 | F64: 456456804793 | G64: tdc | H64: visa | I64: 574 | J64: Shaiel | L64: 5 | M64: =IFERROR(ROUNDUP(VLOOKUP(F64,Accesorio!A:E,IF(L64>5,L64-2,L64),)*E64/IF(L64>5,1.21,1),0)," ") -> 12000 | N64: =IFERROR(VLOOKUP(F64,Accesorio!A:C,3,),"") -> TPU SAM. A04 SILICONA C/MARCA
A65: 45823 | B65: Consumidor final | D65: 5000 | E65: 1 | F65: 21a15tr | G65: caja | H65: efe | J65: Shaiel | L65: 5 | M65: =IFERROR(ROUNDUP(VLOOKUP(F65,Accesorio!A:E,IF(L65>5,L65-2,L65),)*E65/IF(L65>5,1.21,1),0)," ") -> 5000 | N65: =IFERROR(VLOOKUP(F65,Accesorio!A:C,3,),"") -> TPU SAM. A15 TRANS
A66: 45824 | B66: Consumidor final | D66: 14000 | E66: 1 | F66: PRPSA06 | G66: caja | H66: efe | J66: Lucila | L66: 5 | M66: =IFERROR(ROUNDUP(VLOOKUP(F66,Accesorio!A:E,IF(L66>5,L66-2,L66),)*E66/IF(L66>5,1.21,1),0)," ") -> 14000 | N66: =IFERROR(VLOOKUP(F66,Accesorio!A:C,3,),"") -> TPU SAM. A06 TRANS CLEAR PREMIUM REF
A67: 45824 | B67: Consumidor final | D67: 7500 | E67: 1 | F67: HG'FILMS | G67: tdc | H67: visa | I67: 579 | J67: Enzo | L67: 5 | M67: =IFERROR(ROUNDUP(VLOOKUP(F67,Accesorio!A:E,IF(L67>5,L67-2,L67),)*E67/IF(L67>5,1.21,1),0)," ") -> 7500 | N67: =IFERROR(VLOOKUP(F67,Accesorio!A:C,3,),"") -> HIDROGEL FILMINAS CLEAR 180X120
A68: 45824 | B68: Consumidor final | D68: 6000 | E68: 1 | F68: FPG13M | G68: caja | H68: efe | J68: Lucila | L68: 5 | M68: =IFERROR(ROUNDUP(VLOOKUP(F68,Accesorio!A:E,IF(L68>5,L68-2,L68),)*E68/IF(L68>5,1.21,1),0)," ") -> 6000 | N68: =IFERROR(VLOOKUP(F68,Accesorio!A:C,3,),"") -> TPU MOT. G13/G13SE/G23 PUFFER IMP.
A69: 45824 | B69: Consumidor final | D69: 8000 | E69: 1 | F69: mls's89am | G69: caja | H69: efe | J69: Enzo | L69: 5 | M69: =IFERROR(ROUNDUP(VLOOKUP(F69,Accesorio!A:E,IF(L69>5,L69-2,L69),)*E69/IF(L69>5,1.21,1),0)," ") -> 8000 | N69: =IFERROR(VLOOKUP(F69,Accesorio!A:C,3,),"") -> AUR. ML SOUL S89 AMARILLO
A70: 45824 | B70: Consumidor final | D70: 14000 | E70: 1 | F70: PRPMG85 | G70: tdc | H70: master | I70: 580 | J70: Lucila | L70: 5 | M70: =IFERROR(ROUNDUP(VLOOKUP(F70,Accesorio!A:E,IF(L70>5,L70-2,L70),)*E70/IF(L70>5,1.21,1),0)," ") -> 14000 | N70: =IFERROR(VLOOKUP(F70,Accesorio!A:C,3,),"") -> TPU MOT. G85 TRANS CLEAR PREMIUM REF
A71: 45826 | B71: Consumidor final | D71: 7500 | E71: 1 | F71: HG'FILMS | G71: tdc | H71: visa | I71: 581 | J71: Enzo | L71: 5 | M71: =IFERROR(ROUNDUP(VLOOKUP(F71,Accesorio!A:E,IF(L71>5,L71-2,L71),)*E71/IF(L71>5,1.21,1),0)," ") -> 7500 | N71: =IFERROR(VLOOKUP(F71,Accesorio!A:C,3,),"") -> HIDROGEL FILMINAS CLEAR 180X120
A72: 45826 | B72: Consumidor final | D72: 4500 | E72: 1 | F72: FDT'XR10C | G72: caja | H72: efe | J72: Enzo | L72: 5 | M72: =IFERROR(ROUNDUP(VLOOKUP(F72,Accesorio!A:E,IF(L72>5,L72-2,L72),)*E72/IF(L72>5,1.21,1),0)," ") -> 4500 | N72: =IFERROR(VLOOKUP(F72,Accesorio!A:C,3,),"") -> GLASS XIAOMI REDMI 10C
A73: 45826 | B73: Consumidor final | D73: 5500 | E73: 1 | F73: FD9LXR14C | G73: caja | H73: efe | J73: Enzo | L73: 5 | M73: =IFERROR(ROUNDUP(VLOOKUP(F73,Accesorio!A:E,IF(L73>5,L73-2,L73),)*E73/IF(L73>5,1.21,1),0)," ") -> 5500 | N73: =IFERROR(VLOOKUP(F73,Accesorio!A:C,3,),"") -> GLASS FULL XIAOMI REDMI 14C
A74: 45828 | B74: Control de stock | E74: -2 | F74: FD5DME13 | J74: conciliacion | L74: 5 | M74: =IFERROR(ROUNDUP(VLOOKUP(F74,Accesorio!A:E,IF(L74>5,L74-2,L74),)*E74/IF(L74>5,1.21,1),0)," ") -> -11000 | N74: =IFERROR(VLOOKUP(F74,Accesorio!A:C,3,),"") -> GLASS FULL MOT. E13
A75: 45828 | B75: Control de stock | E75: 2 | F75: FD9DG04NE | J75: conciliacion | L75: 5 | M75: =IFERROR(ROUNDUP(VLOOKUP(F75,Accesorio!A:E,IF(L75>5,L75-2,L75),)*E75/IF(L75>5,1.21,1),0)," ") -> 11000 | N75: =IFERROR(VLOOKUP(F75,Accesorio!A:C,3,),"") -> GLASS FULL MOT. G04 / G24
A76: 45828 | B76: Control de stock | E76: 2 | F76: TDNSA16 | J76: conciliacion | L76: 5 | M76: =IFERROR(ROUNDUP(VLOOKUP(F76,Accesorio!A:E,IF(L76>5,L76-2,L76),)*E76/IF(L76>5,1.21,1),0)," ") -> 9000 | N76: =IFERROR(VLOOKUP(F76,Accesorio!A:C,3,),"") -> TPU SAM. A33 DIS. NAC.
A77: 45828 | B77: Control de stock | E77: -2 | F77: 11A16 | J77: conciliacion | L77: 5 | M77: =IFERROR(ROUNDUP(VLOOKUP(F77,Accesorio!A:E,IF(L77>5,L77-2,L77),)*E77/IF(L77>5,1.21,1),0)," ") -> -9000 | N77: =IFERROR(VLOOKUP(F77,Accesorio!A:C,3,),"") -> TPU SAM. A33 NAC. LISO
A78: 45828 | B78: Control de stock | E78: -1 | F78: TDNSA13 | J78: conciliacion | L78: 5 | M78: =IFERROR(ROUNDUP(VLOOKUP(F78,Accesorio!A:E,IF(L78>5,L78-2,L78),)*E78/IF(L78>5,1.21,1),0)," ") -> -4500 | N78: =IFERROR(VLOOKUP(F78,Accesorio!A:C,3,),"") -> TPU SAM. A13 DIS. NAC.
A79: 45828 | B79: Control de stock | E79: 1 | F79: RIGNAC20 | J79: conciliacion | L79: 5 | M79: =IFERROR(ROUNDUP(VLOOKUP(F79,Accesorio!A:E,IF(L79>5,L79-2,L79),)*E79/IF(L79>5,1.21,1),0)," ") -> 4500 | N79: =IFERROR(VLOOKUP(F79,Accesorio!A:C,3,),"") -> TPU SAM. A13 NAC. LISO BRILLO
A80: 45828 | B80: Control de stock | E80: 1 | F80: 23414 | J80: conciliacion | L80: 5 | M80: =IFERROR(ROUNDUP(VLOOKUP(F80,Accesorio!A:E,IF(L80>5,L80-2,L80),)*E80/IF(L80>5,1.21,1),0)," ") -> 4500 | N80: =IFERROR(VLOOKUP(F80,Accesorio!A:C,3,),"") -> TPU MOT. E13 PUFFER CASE
A81: 45828 | B81: Control de stock | E81: -1 | F81: 34633013 | J81: conciliacion | L81: 5 | M81: =IFERROR(ROUNDUP(VLOOKUP(F81,Accesorio!A:E,IF(L81>5,L81-2,L81),)*E81/IF(L81>5,1.21,1),0)," ") -> -4500 | N81: =IFERROR(VLOOKUP(F81,Accesorio!A:C,3,),"") -> TPU MOT. E13 PUFFER CASE DIS.
A82: 45828 | B82: Control de stock | E82: 1 | F82: FDT'A146 | J82: conciliacion | L82: 5 | M82: =IFERROR(ROUNDUP(VLOOKUP(F82,Accesorio!A:E,IF(L82>5,L82-2,L82),)*E82/IF(L82>5,1.21,1),0)," ") -> 4500 | N82: =IFERROR(VLOOKUP(F82,Accesorio!A:C,3,),"") -> GLASS SAM. A14
A83: 45828 | B83: Control de stock | E83: -1 | F83: FDT'A54 | J83: conciliacion | L83: 5 | M83: =IFERROR(ROUNDUP(VLOOKUP(F83,Accesorio!A:E,IF(L83>5,L83-2,L83),)*E83/IF(L83>5,1.21,1),0)," ") -> -4500 | N83: =IFERROR(VLOOKUP(F83,Accesorio!A:C,3,),"") -> GLASS SAM. A54
A84: 45828 | B84: Control de stock | E84: -1 | F84: FDT'A05 | J84: conciliacion | L84: 5 | M84: =IFERROR(ROUNDUP(VLOOKUP(F84,Accesorio!A:E,IF(L84>5,L84-2,L84),)*E84/IF(L84>5,1.21,1),0)," ") -> -4500 | N84: =IFERROR(VLOOKUP(F84,Accesorio!A:C,3,),"") -> GLASS SAM. A05 / A05S / A06
A85: 45828 | B85: Control de stock | E85: 1 | F85: FDT'A055 | J85: conciliacion | L85: 5 | M85: =IFERROR(ROUNDUP(VLOOKUP(F85,Accesorio!A:E,IF(L85>5,L85-2,L85),)*E85/IF(L85>5,1.21,1),0)," ") -> 5000 | N85: =IFERROR(VLOOKUP(F85,Accesorio!A:C,3,),"") -> GLASS SAM. A05 / A05S / A06
... A107: 45828 | B107: Control de stock | E107: -1 | F107: 5262541412378 | J107: conciliacion | L107: 5 | M107: =IFERROR(ROUNDUP(VLOOKUP(F107,Accesorio!A:E,IF(L107>5,L107-2,L107),)*E107/IF(L107>5,1.21,1),0)," ") -> -5000 | N107: =IFERROR(VLOOKUP(F107,Accesorio!A:C,3,),"") -> SOPORTE POP SOCKET PIEDRAS
A108: 45828 | B108: Consumidor final | D108: 15000 | E108: 2 | F108: SILFA15 | G108: tdc | H108: visa | I108: 585 | J108: Enzo | L108: 5 | M108: =IFERROR(ROUNDUP(VLOOKUP(F108,Accesorio!A:E,IF(L108>5,L108-2,L108),)*E108/IF(L108>5,1.21,1),0)," ") -> 15000 | N108: =IFERROR(VLOOKUP(F108,Accesorio!A:C,3,),"") -> TPU SAM. A15 SILICONA FELPA
A109: 45829 | B109: Consumidor final | D109: 9500 | E109: 1 | F109: PRMIP11C | G109: tdc | H109: visa | I109: 586 | J109: Enzo | L109: 5 | M109: =IFERROR(ROUNDUP(VLOOKUP(F109,Accesorio!A:E,IF(L109>5,L109-2,L109),)*E109/IF(L109>5,1.21,1),0)," ") -> 9500 | N109: =IFERROR(VLOOKUP(F109,Accesorio!A:C,3,),"") -> TPU IPH 11 / XR MAGNETICO TRANS COLORES
A110: 45829 | B110: Consumidor final | D110: 9500 | E110: 1 | F110: TPURSA33 | G110: tdc | H110: visa | I110: 587 | J110: Enzo | L110: 5 | M110: =IFERROR(ROUNDUP(VLOOKUP(F110,Accesorio!A:E,IF(L110>5,L110-2,L110),)*E110/IF(L110>5,1.21,1),0)," ") -> 9500 | N110: =IFERROR(VLOOKUP(F110,Accesorio!A:C,3,),"") -> TPU SAM. A33 REF SOFT
A111: 45829 | B111: Consumidor final | D111: 4500 | E111: 1 | F111: fdt'e40 | G111: tdc | H111: visa | I111: 588 | J111: Enzo | L111: 5 | M111: =IFERROR(ROUNDUP(VLOOKUP(F111,Accesorio!A:E,IF(L111>5,L111-2,L111),)*E111/IF(L111>5,1.21,1),0)," ") -> 4500 | N111: =IFERROR(VLOOKUP(F111,Accesorio!A:C,3,),"") -> GLASS MOT. E20/E40
A112: 45829 | B112: Consumidor final | D112: 5500 | E112: 1 | F112: 4715001120 | G112: tdc | H112: visa | I112: 588 | J112: Enzo | L112: 5 | M112: =IFERROR(ROUNDUP(VLOOKUP(F112,Accesorio!A:E,IF(L112>5,L112-2,L112),)*E112/IF(L112>5,1.21,1),0)," ") -> 5500 | N112: =IFERROR(VLOOKUP(F112,Accesorio!A:C,3,),"") -> CAR. PARED CABEZAL USB - 2A KOSMO
A113: 45829 | B113: Consumidor final | D113: 7000 | E113: 1 | F113: fpca14 | G113: tdc | H113: visa | I113: 588 | J113: Enzo | L113: 5 | M113: =IFERROR(ROUNDUP(VLOOKUP(F113,Accesorio!A:E,IF(L113>5,L113-2,L113),)*E113/IF(L113>5,1.21,1),0)," ") -> 7000 | N113: =IFERROR(VLOOKUP(F113,Accesorio!A:C,3,),"") -> TPU SAM. A14 PUFFER IMP. CORAZONES
A114: 45829 | B114: Consumidor final | D114: 15000 | E114: 1 | F114: 025215492570 | G114: caja | H114: efe | J114: Enzo | L114: 5 | M114: =IFERROR(ROUNDUP(VLOOKUP(F114,Accesorio!A:E,IF(L114>5,L114-2,L114),)*E114/IF(L114>5,1.21,1),0)," ") -> 15000 | N114: =IFERROR(VLOOKUP(F114,Accesorio!A:C,3,),"") -> MEMORIA MICROSD 32GB C10 MAXELL
A115: 45829 | B115: Consumidor final | D115: 5500 | E115: 1 | F115: fd5mg05 | G115: caja | H115: efe | J115: Enzo | L115: 5 | M115: =IFERROR(ROUNDUP(VLOOKUP(F115,Accesorio!A:E,IF(L115>5,L115-2,L115),)*E115/IF(L115>5,1.21,1),0)," ") -> 5500 | N115: =IFERROR(VLOOKUP(F115,Accesorio!A:C,3,),"") -> GLASS FULL MOT. G05 / E15
A116: 45829 | B116: Consumidor final | D116: 7500 | E116: 1 | F116: HG'FILMS | G116: caja | H116: efe | J116: Enzo | L116: 5 | M116: =IFERROR(ROUNDUP(VLOOKUP(F116,Accesorio!A:E,IF(L116>5,L116-2,L116),)*E116/IF(L116>5,1.21,1),0)," ") -> 7500 | N116: =IFERROR(VLOOKUP(F116,Accesorio!A:C,3,),"") -> HIDROGEL FILMINAS CLEAR 180X120
A117: 45830 | B117: Consumidor final | D117: 5000 | E117: 1 | F117: 21g05tr | G117: caja | H117: efe | J117: Shaiel | L117: 5 | M117: =IFERROR(ROUNDUP(VLOOKUP(F117,Accesorio!A:E,IF(L117>5,L117-2,L117),)*E117/IF(L117>5,1.21,1),0)," ") -> 5000 | N117: =IFERROR(VLOOKUP(F117,Accesorio!A:C,3,),"") -> TPU MOT. G05 / E15 TRANS
A118: 45830 | B118: Consumidor final | D118: 5000 | E118: 1 | F118: 21G05TR | G118: caja | H118: efe | J118: Shaiel | L118: 5 | M118: =IFERROR(ROUNDUP(VLOOKUP(F118,Accesorio!A:E,IF(L118>5,L118-2,L118),)*E118/IF(L118>5,1.21,1),0)," ") -> 5000 | N118: =IFERROR(VLOOKUP(F118,Accesorio!A:C,3,),"") -> TPU MOT. G05 / E15 TRANS
A119: 45830 | B119: Consumidor final | D119: 5500 | E119: 1 | F119: FD5ME15 | G119: caja | H119: efe | J119: Shaiel | L119: 5 | M119: =IFERROR(ROUNDUP(VLOOKUP(F119,Accesorio!A:E,IF(L119>5,L119-2,L119),)*E119/IF(L119>5,1.21,1),0)," ") -> 5500 | N119: =IFERROR(VLOOKUP(F119,Accesorio!A:C,3,),"") -> GLASS FULL MOT. G05 / E15
A120: 45830 | B120: Consumidor final | D120: 9500 | E120: 1 | F120: T0003 | G120: tdc | H120: visa | I120: 589 | J120: Lucila | L120: 5 | M120: =IFERROR(ROUNDUP(VLOOKUP(F120,Accesorio!A:E,IF(L120>5,L120-2,L120),)*E120/IF(L120>5,1.21,1),0)," ") -> 9500 | N120: =IFERROR(VLOOKUP(F120,Accesorio!A:C,3,),"") -> TPU MOT. G22/E32 RUBBER
A121: 45830 | B121: Consumidor final | D121: 4000 | E121: 1 | F121: TDNSA17 | G121: caja | H121: efe | J121: Lucila | L121: 5 | M121: =IFERROR(ROUNDUP(VLOOKUP(F121,Accesorio!A:E,IF(L121>5,L121-2,L121),)*E121/IF(L121>5,1.21,1),0)," ") -> 4000 | N121: =IFERROR(VLOOKUP(F121,Accesorio!A:C,3,),"") -> TPU SAM. A03 DIS. NAC.
...

Sheet Accesorio
A1: CodigoCeiba | B1: Categorias | C1: Descripción | D1: PrecioMayorista | E1: PrecioPúblico | F1: Actual | G1: Inicial | H1: =IF(SUM(CajaAcc!E:E)+SUM(F:F)-SUM(G:G)=0,"BIEN","HAY ERRORES") -> BIEN
A2: 17078 | B2: AURICULAR | C2: AUR. BT BUD A6S MiPods 5.0 | D2: 5568 | E2: 17000 | F2: =-SUMIF(CajaAcc!F:F,A2,CajaAcc!E:E)+G2 -> 2 | G2: 2
A3: 6918888964540 | B3: AURICULAR | C3: AUR. BT BUD BALI BL-207 | D3: 9278 | E3: 25000 | F3: =-SUMIF(CajaAcc!F:F,A3,CajaAcc!E:E)+G3 -> 0 | G3: 0
A4: 8235BL207'CE | B4: AURICULAR | C4: AUR. BT BUD BALI BL-207 | D4: 9278 | E4: 25000 | F4: =-SUMIF(CajaAcc!F:F,A4,CajaAcc!E:E)+G4 -> 0 | G4: 0
A5: 8235BL207'BL | B5: AURICULAR | C5: AUR. BT BUD BALI BL-207 | D5: 9278 | E5: 25000 | F5: =-SUMIF(CajaAcc!F:F,A5,CajaAcc!E:E)+G5 -> 2 | G5: 2
A6: 8235BL207'NE | B6: AURICULAR | C6: AUR. BT BUD BALI BL-207 | D6: 9278 | E6: 25000 | F6: =-SUMIF(CajaAcc!F:F,A6,CajaAcc!E:E)+G6 -> 0 | G6: 0
A7: 8235BL207'RO | B7: AURICULAR | C7: AUR. BT BUD BALI BL-207 | D7: 9278 | E7: 25000 | F7: =-SUMIF(CajaAcc!F:F,A7,CajaAcc!E:E)+G7 -> 0 | G7: 0
A8: JK601 | B8: AURICULAR | C8: AUR. BT BUD C/OREJERAS JK601 CRYSTAL V5.4 | D8: 8667 | E8: 23500 | F8: =-SUMIF(CajaAcc!F:F,A8,CajaAcc!E:E)+G8 -> 0 | G8: 0
A9: AUR'TWSS100NE | B9: AURICULAR | C9: AUR. BT BUD C/OREJERAS SOUL S100 | D9: 24209 | E9: 45500 | F9: =-SUMIF(CajaAcc!F:F,A9,CajaAcc!E:E)+G9 -> 0 | G9: 0
A10: 16729 | B10: AURICULAR | C10: AUR. BT BUD CAKE TWS 5.0 | D10: 5568 | E10: 17000 | F10: =-SUMIF(CajaAcc!F:F,A10,CajaAcc!E:E)+G10 -> 1 | G10: 1
A11: 16820 | B11: AURICULAR | C11: AUR. BT BUD CANDY TWS 5.0 | D11: 5568 | E11: 17000 | F11: =-SUMIF(CajaAcc!F:F,A11,CajaAcc!E:E)+G11 -> 1 | G11: 1
A12: 17080 | B12: AURICULAR | C12: AUR. BT BUD F9 5.0 | D12: 5568 | E12: 17000 | F12: =-SUMIF(CajaAcc!F:F,A12,CajaAcc!E:E)+G12 -> 0 | G12: 0
A13: I12STWS | B13: AURICULAR | C13: AUR. BT BUD I12S TWS 5.0 | D13: 5568 | E13: 17000 | F13: =-SUMIF(CajaAcc!F:F,A13,CajaAcc!E:E)+G13 -> 0 | G13: 0
... A2826: 21GTMCMX164 | B2826: TPU | C2826: TPU MOT. G4 MYSTIC | D2826: 896 | E2826: 1000 | F2826: =-SUMIF(CajaAcc!F:F,A2826,CajaAcc!E:E)+G2826 -> 0 | G2826: 0
A2827: 21VMG4YDEP | B2827: TPU | C2827: TPU MOT. G4 PLAY DIS. LIQUIDO | D2827: 896 | E2827: 1000 | F2827: =-SUMIF(CajaAcc!F:F,A2827,CajaAcc!E:E)+G2827 -> 0 | G2827: 0 | H2827: 15600
A2828: 21ZTCMG4P | B2828: TPU | C2828: TPU MOT. G4 PLUS DIS. CLOTH | D2828: 896 | E2828: 1000 | F2828: =-SUMIF(CajaAcc!F:F,A2828,CajaAcc!E:E)+G2828 -> 0 | G2828: 0
A2829: tpuice'xt1641d01 | B2829: TPU | C2829: TPU MOT. G4 PLUS DIS. ICE CREAM | D2829: 896 | E2829: 1000 | F2829: =-SUMIF(CajaAcc!F:F,A2829,CajaAcc!E:E)+G2829 -> 0 | G2829: 0
A2830: tpuice'xt1641d02 | B2830: TPU | C2830: TPU MOT. G4 PLUS DIS. ICE CREAM | D2830: 896 | E2830: 1000 | F2830: =-SUMIF(CajaAcc!F:F,A2830,CajaAcc!E:E)+G2830 -> 0 | G2830: 0
A2831: 21VMOTG4PDEP | B2831: TPU | C2831: TPU MOT. G4 PLUS DIS. LIQUIDO | D2831: 896 | E2831: 1000 | F2831: =-SUMIF(CajaAcc!F:F,A2831,CajaAcc!E:E)+G2831 -> 0 | G2831: 0
A2832: 21ZTPXMG4P | B2832: TPU | C2832: TPU MOT. G4 PLUS DIS. PIXEL | D2832: 896 | E2832: 1000 | F2832: =-SUMIF(CajaAcc!F:F,A2832,CajaAcc!E:E)+G2832 -> 0 | G2832: 0
A2833: 21TPDMG4PU | B2833: TPU | C2833: TPU MOT. G4 PLUS DIS. SUBLIMADOS | D2833: 896 | E2833: 1000 | F2833: =-SUMIF(CajaAcc!F:F,A2833,CajaAcc!E:E)+G2833 -> 0 | G2833: 0
A2834: tpue'xt1641fu | B2834: TPU | C2834: TPU MOT. G4 PLUS ELECTRO | D2834: 896 | E2834: 1000 | F2834: =-SUMIF(CajaAcc!F:F,A2834,CajaAcc!E:E)+G2834 -> 0 | G2834: 0
A2835: tpumd'xt1641d01oc | B2835: TPU | C2835: TPU MOT. G4 PLUS MIRROR FLOWERS | D2835: 896 | E2835: 1000 | F2835: =-SUMIF(CajaAcc!F:F,A2835,CajaAcc!E:E)+G2835 -> 0 | G2835: 0
A2836: tpumd'xt1641d01ve | B2836: TPU | C2836: TPU MOT. G4 PLUS MIRROR FLOWERS | D2836: 896 | E2836: 1000 | F2836: =-SUMIF(CajaAcc!F:F,A2836,CajaAcc!E:E)+G2836 -> 0 | G2836: 0
A2837: tpumd'xt1641d02oc | B2837: TPU | C2837: TPU MOT. G4 PLUS MIRROR STARS | D2837: 896 | E2837: 1000 | F2837: =-SUMIF(CajaAcc!F:F,A2837,CajaAcc!E:E)+G2837 -> 0 | G2837: 0
A2838: TPURSD'XT1641 | B2838: TPU | C2838: TPU MOT. G4 PLUS REF SOFT | D2838: 896 | E2838: 1000 | F2838: =-SUMIF(CajaAcc!F:F,A2838,CajaAcc!E:E)+G2838 -> 0 | G2838: 0
A2839: tpuag'xt1641ro | B2839: TPU | C2839: TPU MOT. G4 PLUS TRANS | D2839: 896 | E2839: 1000 | F2839: =-SUMIF(CajaAcc!F:F,A2839,CajaAcc!E:E)+G2839 -> 0 | G2839: 0
... A4156: TPURSA06 | B4156: TPU | C4156: TPU SAM. A06 REF SOFT | D4156: 1636 | E4156: 5000 | F4156: =-SUMIF(CajaAcc!F:F,A4156,CajaAcc!E:E)+G4156 -> 1 | G4156: 0

Sheet TablaPuntos
A1: ACCESORIO | B1: PROPIO | C1: PREPAGA | D1: BAF | E1: R2G | F1: R4G | G1: R7G | H1: R10G | I1: R20G | J1: R30G | K1: P280 | L1: P2G | M1: P4G | N1: P7G | O1: P10G | P1: P20G | Q1: P30G | R1: PORTAP | S1: Cater | U1: Objetivo
A2: 200 | B2: 150 | C2: 1000 | D2: 1 | E2: 1 | F2: 1 | G2: 1 | H2: 1 | I2: 1 | J2: 1 | K2: 1 | L2: 1 | M2: 1 | N2: 1 | O2: 1 | P2: 1 | Q2: 1 | R2: 1 | S2: 1 | U2: Operaciones
A3: D | B3: D | C3: D | U3: 118 | V3: completar según Objetivo Sucursal

Sheet Objetivos
A1: OBJETIVOS
A2: ACCESORIO | B2: PROPIO | C2: PREPAGA | D2: BAF | E2: R2G | F2: R4G | G2: R7G | H2: R10G | I2: R20G | J2: R30G | K2: P280 | L2: P2G | M2: P4G | N2: P7G | O2: P10G | P2: P20G | Q2: P30G | R2: PORTAP | S2: Cater | T2: Total Operaciones | U2: Puntos Objetivos | V2: %Logrado
A3: =IF(TablaPuntos!A3 = "D",A7/TablaPuntos!A2,A7*TablaPuntos!A2) -> 4177.18 | B3: =IF(TablaPuntos!B3 = "D",B7/TablaPuntos!B2,B7*TablaPuntos!B2) -> 0 | C3: =IF(TablaPuntos!C3 = "D",C7/TablaPuntos!C2,C7*TablaPuntos!C2) -> 0 | D3: =IF(TablaPuntos!D3 = "D",D7/TablaPuntos!D2,D7*TablaPuntos!D2) -> 13 | E3: =IF(TablaPuntos!E3 = "D",E7/TablaPuntos!E2,E7*TablaPuntos!E2) -> 39 | F3: =IF(TablaPuntos!F3 = "D",F7/TablaPuntos!F2,F7*TablaPuntos!F2) -> 9 | G3: =IF(TablaPuntos!G3 = "D",G7/TablaPuntos!G2,G7*TablaPuntos!G2) -> 3 | H3: =IF(TablaPuntos!H3 = "D",H7/TablaPuntos!H2,H7*TablaPuntos!H2) -> 1 | ... S3: =IF(TablaPuntos!S3 = "D",S7/TablaPuntos!S2,S7*TablaPuntos!S2) -> 35 | T3: =SUM(D3:S3) -> 119 | U3: =TablaPuntos!U3 -> 118 | V3: =T3/TablaPuntos!U3 -> 1.0084746
A5: INGRESOS
A6: ACCESORIO | B6: PROPIO | C6: PREPAGA | D6: BAF | E6: R2G | F6: R4G | G6: R7G | H6: R10G | I6: R20G | J6: R30G | K6: P280 | L6: P2G | M6: P4G | N6: P7G | O6: P10G | P6: P20G | Q6: P30G | R6: PORTAP | S6: Cater
A7: =SUMIF(CAJA!$G:$G,A6,CAJA!$D:$D) -> 835436 | B7: =SUMIF(CAJA!$G:$G,B6,CAJA!$D:$D)-SUMIF(CAJA!$H:$H,"SIM*",CAJA!$D:$D) -> 0 | C7: =SUMIF(CAJA!$G:$G,C6,CAJA!$D:$D) -> 0 | D7: =SUMIF(CAJA!$G:$G,D6,CAJA!$F:$F) -> 13 | E7: =SUMIF(CAJA!$G:$G,E6,CAJA!$F:$F) -> 39 | F7: =SUMIF(CAJA!$G:$G,F6,CAJA!$F:$F) -> 9 | G7: =SUMIF(CAJA!$G:$G,G6,CAJA!$F:$F) -> 3 | H7: =SUMIF(CAJA!$G:$G,H6,CAJA!$F:$F) -> 1 | I7: =SUMIF(CAJA!$G:$G,I6,CAJA!$F:$F) -> 0 | J7: =SUMIF(CAJA!$G:$G,J6,CAJA!$F:$F) -> 1 | K7: =SUMIF(CAJA!$G:$G,K6,CAJA!$F:$F) -> 0 | ... S7: =SUMIF(CAJA!$G:$G,S6,CAJA!$F:$F) -> 35
A9: 45809 | B9: Operaciones | C9: 0.9 | D9: 1 | E9: 1.1 | F9: 1.25
A10: Comisiones | C10: 50000 | D10: 70000 | E10: 100000 | F10: 150000
A11: 1C | B11: 80 | C11: 72 | D11: 80 | E11: 88 | F11: 100
A12: 2N | B12: 135 | C12: 121 | D12: 135 | E12: 148 | F12: 168
A13: 3RO | B13: 118 | C13: 106 | D13: 118 | E13: 130 | F13: 147
A14: M | B14: 45 | C14: 40 | D14: 45 | E14: 49 | F14: 56
A15: 6C | B15: 45 | C15: 75 | D15: 83 | E15: 91 | F15: 103
G17: JUNIO 2025
A19: OBJETIVOS
A20: ACCESORIO | B20: PROPIO | C20: PREPAGA | D20: BAF | E20: REGULAR | F20: PORTABILIDAD | G20: PORTAP | H20: Cater
A21: DIVIDE 200 | B21: DIVIDE 150 | D21: 20 | E21: 15 * VENDEDOR | F21: 10 * VENDEDOR | G21: 10 | H21: 10 * VENDEDOR

Sheet TDC
A1: Calcular | I1: =IF(OR(A3=I2,A3=I3,A3=I4,A3=I5),"Master",A3) -> COUTASIMPLE | Q1: Calculador CUOTA SIN INTERES | Y1: =IF(OR(Q3=I2,Q3=I3,Q3=I4,Q3=I5),"Master",Q3) -> COUTASIMPLE
A2: Tarjeta | B2: Precio Contado | C2: Cantidad de cuotas | D2: Valor Cuota | E2: Monto | I2: Visa | Q2: Tarjeta | R2: Precio Contado | S2: Cantidad de cuotas | T2: Asentar en Caja | U2: Valor Cuota Cliente | AG2: TARJETA POR
A3: COUTASIMPLE | B3: 320000 | C3: 12 | D3: =IFERROR(VLOOKUP(F3,F7:G49,2,),"")*B3/1000 -> 32320 | E3: =C3*D3 -> 387840 | F3: =I1&C3 -> COUTASIMPLE12 | I3: Master | Q3: COUTASIMPLE | R3: 200000 | S3: 6 | T3: =MROUND(IFERROR(R3/VLOOKUP(V3,F7:L35,7,),""),100) -> 179500 | U3: =AG3/S3 -> 33333.333 | V3: =Y1&S3 -> COUTASIMPLE6 | AG3: =IF(S3=9,R3*1.1,0)+IF(S3=12,R3*1.15,0)+IF(S3<9,R3,0) -> 200000
I4: American
A5: Tabla | I5: Cabal
A6: Tarjeta | B6: Precio Contado | C6: Cantidad de cuotas | D6: Valor Cuota | E6: Monto | I6: CoutaSimple
A7: Master | B7: 1000 | C7: 1 | D7: 1070 | E7: 1070 | F7: =A7&C7 -> Master1 | G7: =D7 -> 1070 | I7: Maestro | K7: =C7 -> 1 | L7: =E7/B7 -> 1.07
A8: Master | B8: 1000 | C8: 2 | D8: 620 | E8: 1240 | F8: =A8&C8 -> Master2 | G8: =D8 -> 620 | I8: NaranjaZ | K8: =C8 -> 2 | L8: =E8/B8 -> 1.24
A9: Master | B9: 1000 | C9: 3 | D9: 450 | E9: 1350 | F9: =A9&C9 -> Master3 | G9: =D9 -> 450 | I9: Naranja$ | K9: =C9 -> 3 | L9: =E9/B9 -> 1.35
A10: Master | B10: 1000 | C10: 6 | D10: 272 | E10: 1630 | F10: =A10&C10 -> Master6 | G10: =D10 -> 272 | I10: Fertil | K10: =C10 -> 6 | L10: =E10/B10 -> 1.63
A11: Master | B11: 1000 | C11: 12 | D11: 193 | E11: 2320 | F11: =A11&C11 -> Master12 | G11: =D11 -> 193 | K11: =C11 -> 12 | L11: =E11/B11 -> 2.32
A12: Master | B12: 1000 | C12: 18 | D12: 178 | E12: 3200 | F12: =A12&C12 -> Master18 | G12: =D12 -> 178 | K12: =C12 -> 18 | L12: =E12/B12 -> 3.2
A13: Master | B13: 1000 | C13: 24 | D13: 150 | E13: 3600 | F13: =A13&C13 -> Master24 | G13: =D13 -> 150 | K13: =C13 -> 24 | L13: =E13/B13 -> 3.6
A14: CoutaSimple | B14: 1000 | C14: 3 | D14: 354 | E14: 1060 | F14: =A14&C14 -> CoutaSimple3 | G14: =D14 -> 354 | K14: =C14 -> 3 | L14: 1.0603 | M14: 6.03
A15: CoutaSimple | B15: 1000 | C15: 6 | D15: 186 | E15: 1116 | F15: =A15&C15 -> CoutaSimple6 | G15: =D15 -> 186 | K15: =C15 -> 6 | L15: 1.1145 | M15: 11.45
A16: CoutaSimple | B16: 1000 | C16: 9 | D16: 129 | E16: 1161 | F16: =A16&C16 -> CoutaSimple9 | G16: =D16 -> 129 | K16: =C16 -> 9 | L16: 1.1645 | M16: 16.45
A17: CoutaSimple | B17: 1000 | C17: 12 | D17: 101 | E17: 1212 | F17: =A17&C17 -> CoutaSimple12 | G17: =D17 -> 101 | K17: =C17 -> 12 | L17: 1.2107 | M17: 21.07
A18: Fertil | B18: 1000 | C18: 3 | D18: 423 | E18: 1269 | F18: =A18&C18 -> Fertil3 | G18: =D18 -> 423 | K18: =C18 -> 3 | L18: =E18/B18 -> 1.269
A19: Fertil | B19: 1000 | C19: 6 | D19: 212 | E19: 1270 | F19: =A19&C19 -> Fertil6 | G19: =D19 -> 212 | K19: =C19 -> 6 | L19: =E19/B19 -> 1.27
A20: Fertil | B20: 1000 | C20: 9 | D20: 161 | E20: 1450 | F20: =A20&C20 -> Fertil9 | G20: =D20 -> 161 | K20: =C20 -> 9 | L20: =E20/B20 -> 1.45
A21: Fertil | B21: 1000 | C21: 12 | D21: 142 | E21: 1700 | F21: =A21&C21 -> Fertil12 | G21: =D21 -> 142 | K21: =C21 -> 12 | L21: =E21/B21 -> 1.7
A22: NaranjaZ | B22: 1000 | C22: 1 | D22: 1240 | E22: 1240 | F22: =A22&C22 -> NaranjaZ1 | G22: =D22 -> 1240 | K22: =C22 -> 1 | L22: =E22/B22 -> 1.24
A23: Naranja$ | B23: 1000 | C23: 1 | D23: 1020 | E23: 102 | F23: =A23&C23 -> Naranja$1 | G23: =D23 -> 1020 | K23: =C23 -> 1 | L23: =E23/B23 -> 0.102
A24: Naranja$ | B24: 1000 | C24: 12 | D24: 200 | E24: 2400 | F24: =A24&C24 -> Naranja$12 | G24: =D24 -> 200 | K24: =C24 -> 12 | L24: =E24/B24 -> 2.4
A25: Maestro | B25: 1000 | C25: 1 | D25: 1000 | E25: 1000 | F25: =A25&C25 -> Maestro1 | G25: =D25 -> 1000 | K25: =C25 -> 1 | L25: =E25/B25 -> 1
F26: =A26&C26 | G26: =D26 -> 0 | K26: =C26 -> 0 | L26: =E26/B26 -> #DIV/0!
F27: =A27&C27 | G27: =D27 -> 0 | K27: =C27 -> 0 | L27: =E27/B27 -> #DIV/0!
F28: =A28&C28 | G28: =D28 -> 0 | K28: =C28 -> 0 | L28: =E28/B28 -> #DIV/0!
F29: =A29&C29 | G29: =D29 -> 0 | K29: =C29 -> 0 | L29: =E29/B29 -> #DIV/0!
F30: =A30&C30 | G30: =D30 -> 0 | K30: =C30 -> 0 | L30: =E30/B30 -> #DIV/0!
F31: =A31&C31 | G31: =D31 -> 0 | K31: =C31 -> 0 | L31: =E31/B31 -> #DIV/0!
F32: =A32&C32 | G32: =D32 -> 0 | K32: =C32 -> 0 | L32: =E32/B32 -> #DIV/0!
F33: =A33&C33 | G33: =D33 -> 0 | K33: =C33 -> 0 | L33: =E33/B33 -> #DIV/0!
F34: =A34&C34 | G34: =D34 -> 0 | K34: =C34 -> 0 | L34: =E34/B34 -> #DIV/0!
F35: =A35&C35 | G35: =D35 -> 0 | K35: =C35 -> 0 | L35: =E35/B35 -> #DIV/0!
